Workbook
Name Act_Names: [1]Lookups!$A$7:$B$21
Name Analysis: [1]!Analysis4[#Data]
Name AUTHORITATIVEREFERENCE: #REF!
Name Capabilities: #REF!
Name Capabilities: #REF!
Name CapabilityIDs_nr: [2]!CapabilityID_tbl[CapabilityID]
Name DoahAmanda: '[3]Doah and Amanda'!$A$2:$F$28
Name Effectiveness: #REF!
Name ETSNEXT_Deloite_Digital_Usability_Report__September_2016: #REF!
Name HollyTammyAlexDotti: '[4]Holly, Tammy, Alex, and Dotti'!$A$2:$F$28
Name HRJobGroup: [5]!HRJobTable[[#All],[Group]:[Occupation Group]]
Name HRJobSeries: [5]!HRJobTable[[#All],[Occupation Series Code]:[Occupation Series Label]]
Name HRJobTitle: [5]!HRJobTable[[#All],[Occupation Title Code]:[Occupation Title Label]]
Name LookupByCapRef: #REF!
Name LookupByCapRef: #REF!
Name Priority: '[6]Cross-cut Functs'!$Q$7:$Q$10
Name Service_Activity_ID_Names: [2]!Service_Activities_tbl[ServiceActivityName]
Name ServiceActivities: 'FFM-Functions-Activities'!$1:$1048576
Name ServiceFunctions: #REF!
Name SteveAngie: '[4]Steve and Angie'!$A$2:$F$28

Sheet Cover Page
A1: Draft/Pre-Decisional
A12: Financial Management (FM) Solution/Service Definition Template
A16: As of: May 26, 2021
G19: Draft/Pre-Decisional
G20: This RFI (Request for Information) is issued solely for market research and planning purposes. The RFI does not constitute a solicitation or a commitment to a particular acquisition strategy. The RFI is intended to get industry feedback on the vision for the FM QSMO Marketplace, which includes core financial system and other financial management services and solutions. Nothing in this document should be construed as a final government decision upon which industry should take action and the RFI is subject to change. Treasury is not seeking proposals at this time and will not consider unsolicited proposals provided in response to the RFI. All information received in response to the RFI that is marked as proprietary will be handled accordingly. Responses to this notice are not offers and cannot be accepted by the Government to form a binding contract. Responders are solely responsible for all expenses associated with responding to the RFI.

Sheet Overview
B1: Draft/Pre-Decisional
B2: This RFI (Request for Information) is issued solely for market research and planning purposes. The RFI does not constitute a solicitation or a commitment to a particular acquisition strategy. The RFI is intended to get industry feedback on the vision for the FM QSMO Marketplace, which includes core financial system and other financial management services and solutions. Nothing in this document should be construed as a final government decision upon which industry should take action and the RFI is subject to change. Treasury is not seeking proposals at this time and will not consider unsolicited proposals provided in response to the RFI. All information received in response to the RFI that is marked as proprietary will be handled accordingly. Responses to this notice are not offers and cannot be accepted by the Government to form a binding contract. Responders are solely responsible for all expenses associated with responding to the RFI.
A3: Overview
A4: ='Cover Page'!A16 -> As of: May 26, 2021
A5: FM Solution/Service Definition Template
A6: Workbook Tab Name | B6: Description
A7: Overview | B7: This tab lists each workbook tab and provides an explanation of the tab's contents
A8: Solution/Service Definition Tabs:
A9: FM Sol-Serv Def Template FM Sol-Serv Def Example - SaaS FM Sol-Serv Def Example - PaaS FM Sol-Serv Def Example - Audit
A10: Objective | B10: These tabs provide the template and examples of FM solution/service package definitions indicating what components are included and excluded from an FM solution/service package.
A11: Provider Name | B11: Identifies the name of the provider of the FM solution/service
A12: FM Solution/Service Package Name | B12: Identifies the name of the FM solution/service offering. The term "package" is used because a single provider may offer multiple variations of their FM solution/service offering (e.g., Core FS using commercial IaaS subservices and Core FS using classified government cloud IaaS subservices).
A13: FM Solution/Service Package Short Description | B13: Provides a short description of the FM solution/service offering, including the general scope and the intended use by the Service Customer
A14: FFM Functions: Activities | B14: For each FFM Function/Activity listed, indicates which components are included in (enabled or performed) or excluded from the FM solution/service package. This is referred to as the "Business View" of the FM solution/service package being offered.
A15: Service Delivery Layers and Towers: Sub-Towers | B15: For each Sub-Tower within a Tower within a Service Delivery Layer, indicates which components are included in or excluded from the FM solution/service package. This is referred to as the "Asset View" of the FM solution/service package being offered.
A16: Service Delivery Resources and Cost Pools | B16: For each Cost Pool within a Service Delivery Resource category, indicates which components are included in or excluded from the FM solution/service package. Note that "external labor" and "outside service" refer to sub-contractors or sub-services the Service Provider manages and integrates into the FM solution/service offering or to which the Service Provider needs access.
A17: Indicator | B17: N/A = None of the components are applicable to delivering the service or using the solution INCL = All applicable components are included in delivering the service or using the solution EXCL/R* = Components are not included in solution/service offering, but are required when delivering the service or using the solution EXCL/O* = Components are not included in solution/service offering, but can be optional when delivering the service or using the solution PRTL/NA* = Some components are not included in solution/service offering because they are not applicable when delivering the service or using the solution PRTL/R* = Some components are not included in solution/service offering, but are required when delivering the service or using the solution PRTL/O* = Some components are not included in solution/service offering, but can be optional when delivering the service or using the solution * = Explanation required e.g., the specific components or resources excluded and/or to be provided by Service Customer (e.g., GFE)
A18: Additional Explanation | B18: Further explanation of what is included or excluded in an FM solution/service package and expectations of assets to be provided by Service Customers
A19: Additional Tabs in this Workbook are provided for reference purposes only.
A20: FFM-Functions-Activities Tab
A21: Objective | B21: This tab provides a list and description of FFM Functions and Activities for reference purposes
A22: ServiceFunctionID | B22: This column provides the unique identifier for the Service Function.
A23: ServiceFunctionName | B23: This column provides the short name for the FIBF Service Function.
A24: Service Activity ID | B24: This column provides the unique identifier for the Service Activity.
A25: Service Activity Name | B25: This column provides the short name for the FIBF Service Activity.
A26: Service Activity Description | B26: This column provides a description of the FIBF Service Activity.
A27: Serv Delivery Layers-Resources Tab
A28: Objective | B28: This tab includes a high-level graphic and description of Service Delivery Layers and Service Delivery Resources for reference purposes.
A29: Towers-SubTowers Tab
A30: Objective | B30: This tab provides a high-level list and description of the commercial TBM Towers/Sub-Towers plus government-defined extensions to commercial TBM Towers/Sub-Towers for reference purposes. The government-defined extensions are used to fully account for other anticipated service delivery components and costs not explicitly addressed in the commercial TBM Tower/Sub-Tower descriptions.
A31: Cost Pools-SubCost PoolsTab
A32: Objective | B32: This tab provides a high-level list and description of the TBM Cost Pools and Sub-Cost Pools
A33: Service Components List Tab
A34: Objective | B34: Provides a detailed list of service components that can be filtered by Service Delivery Layer, Towers/Sub-Towers, Service Delivery Resources, and Cost Pools/Sub-Cost Pools. This list can be used as a checklist to ensure all service-solution components have been considered when defining what is included/excluded in a service package or to further understand which components should be accounted for in which category (Service Delivery Layer, Service Delivery Resources, Towers/Sub-Towers, and Cost Pools/Sub-Cost Pools).
A35: ITIL Tab
A36: Objective | B36: This tab provides a list of the Information Technology Infrastructure Library (ITIL) Practices referenced in the Service Components List tab.

Sheet FM Sol-Serv Def Template
B1: Draft/Pre-Decisional
B2: This RFI (Request for Information) is issued solely for market research and planning purposes. The RFI does not constitute a solicitation or a commitment to a particular acquisition strategy. The RFI is intended to get industry feedback on the vision for the FM QSMO Marketplace, which includes core financial system and other financial management services and solutions. Nothing in this document should be construed as a final government decision upon which industry should take action and the RFI is subject to change. Treasury is not seeking proposals at this time and will not consider unsolicited proposals provided in response to the RFI. All information received in response to the RFI that is marked as proprietary will be handled accordingly. Responses to this notice are not offers and cannot be accepted by the Government to form a binding contract. Responders are solely responsible for all expenses associated with responding to the RFI.
A3: FM Solution/Service Definition Template
A4: ='Cover Page'!A16 -> As of: May 26, 2021
A6: Provider Name:
A7: FM Solution/Service Package Name:
A8: FM Solution/Service Package Short Description:
A9: Business View | B9: Draft/Pre-Decisional
A10: FFM Functions: Activities | B10: Indicator | C10: Additional Explanation
A11: =CONCATENATE('FFM-Functions-Activities'!B3,": ",'FFM-Functions-Activities'!D3) -> Budget Execution: Budget Setup and Maintenance
A12: =CONCATENATE('FFM-Functions-Activities'!B4,": ",'FFM-Functions-Activities'!D4) -> Budget Execution: Fund Allocation and Control
A13: =CONCATENATE('FFM-Functions-Activities'!B5,": ",'FFM-Functions-Activities'!D5) -> Budget Execution: Budgetary Reporting
A14: =CONCATENATE('FFM-Functions-Activities'!B6,": ",'FFM-Functions-Activities'!D6) -> Financial Asset Information Management: Financial Asset Information Processing - Property, Plant, and Equipment
A15: =CONCATENATE('FFM-Functions-Activities'!B7,": ",'FFM-Functions-Activities'!D7) -> Financial Asset Information Management: Financial Asset Information Processing - Loans
A16: =CONCATENATE('FFM-Functions-Activities'!B8,": ",'FFM-Functions-Activities'!D8) -> Financial Asset Information Management: Financial Asset Information Processing - Heritage Assets and Stewardship Land
A17: =CONCATENATE('FFM-Functions-Activities'!B9,": ",'FFM-Functions-Activities'!D9) -> Financial Asset Information Management: Financial Asset Information Processing - Federal Oil and Gas Resources
A18: =CONCATENATE('FFM-Functions-Activities'!B10,": ",'FFM-Functions-Activities'!D10) -> Financial Asset Information Management: Financial Asset Information Processing - Other Federal Assets
A19: =CONCATENATE('FFM-Functions-Activities'!B11,": ",'FFM-Functions-Activities'!D11) -> Financial Asset Information Management: Financial Asset Information Reporting
A20: =CONCATENATE('FFM-Functions-Activities'!B12,": ",'FFM-Functions-Activities'!D12) -> Payable Management: Payee Setup and Maintenance
A21: =CONCATENATE('FFM-Functions-Activities'!B13,": ",'FFM-Functions-Activities'!D13) -> Payable Management: Obligation Management
A22: =CONCATENATE('FFM-Functions-Activities'!B14,": ",'FFM-Functions-Activities'!D14) -> Payable Management: Payment Processing - Intragovernmental Payments
... A64: =CONCATENATE('FFM-Functions-Activities'!B56,": ",'FFM-Functions-Activities'!D56) -> Financial / Performance Reporting: Internal Control/Compliance Reviews
A66: Asset View
A67: Service Delivery Resources: | B67: Technology | H67: Workforce | J67: Advisory | L67: Additional Explanation
A68: Cost Pools: | B68: Facilities | C68: Telecom-Network | D68: Hardware | E68: Software | F68: Internal Services | G68: Outside Services | H68: Internal Labor | I68: External Labor | J68: Internal Labor | K68: External Labor
A69: Service Delivery Layers and Towers: Sub-Towers
A70: SL0: Service Delivery Management
A71: IT Management: IT Management and Strategic Planning
A72: IT Management: Enterprise Architecture
A73: IT Management: IT Finance
A74: IT Management: IT Vendor Management
A75: IT Management: IT Human Capital Management
A76: IT Management: IT Personnel Travel
A77: Delivery: IT Service Management
A78: Delivery: Program, Product & Project Management
A79: Delivery: Client Management
A80: Delivery: Operations Center
... A145: Compliance & Controls: Internal Control & Audit

Sheet FM Sol-Serv Def Example - SaaS
B1: Draft/Pre-Decisional
B2: This RFI (Request for Information) is issued solely for market research and planning purposes. The RFI does not constitute a solicitation or a commitment to a particular acquisition strategy. The RFI is intended to get industry feedback on the vision for the FM QSMO Marketplace, which includes core financial system and other financial management services and solutions. Nothing in this document should be construed as a final government decision upon which industry should take action and the RFI is subject to change. Treasury is not seeking proposals at this time and will not consider unsolicited proposals provided in response to the RFI. All information received in response to the RFI that is marked as proprietary will be handled accordingly. Responses to this notice are not offers and cannot be accepted by the Government to form a binding contract. Responders are solely responsible for all expenses associated with responding to the RFI.
A3: FM Solution/Service Definition Example - Core FS SaaS
A4: ='Cover Page'!A16 -> As of: May 26, 2021
A6: Provider Name: | B6: ABC Company
A7: FM Solution/Service Package Name: | B7: ABC Core FS Software-as-a-Service (SaaS)
A8: FM Solution/Service Package Short Description: | B8: ABC Core FS SaaS offers capabilities that enable customers to perform all FIBF FFM Functions, is fully compliant with Core FS Baseline Solution standards, and provides a full set of technical and operational support services, including Tier 1 service desk support.
A9: Business View
A10: FFM Functions: Activities | B10: Indicator | C10: Additional Explanation
A11: =CONCATENATE('FFM-Functions-Activities'!B3,": ",'FFM-Functions-Activities'!D3) -> Budget Execution: Budget Setup and Maintenance | B11: INCL
A12: =CONCATENATE('FFM-Functions-Activities'!B4,": ",'FFM-Functions-Activities'!D4) -> Budget Execution: Fund Allocation and Control | B12: INCL | C12: The required standard BIE with other lines of business (Functional Areas) is provided to automate execution of funds availability checks
A13: =CONCATENATE('FFM-Functions-Activities'!B5,": ",'FFM-Functions-Activities'!D5) -> Budget Execution: Budgetary Reporting | B13: INCL | C13: The required standard set of FM reports/information extracts are provided; agency-specific reports/information extracts can be developed and provided for an additional cost.
A14: =CONCATENATE('FFM-Functions-Activities'!B6,": ",'FFM-Functions-Activities'!D6) -> Financial Asset Information Management: Financial Asset Information Processing - Property, Plant, and Equipment | B14: INCL | C14: Financial asset information will be recorded using a journal voucher.
A15: =CONCATENATE('FFM-Functions-Activities'!B7,": ",'FFM-Functions-Activities'!D7) -> Financial Asset Information Management: Financial Asset Information Processing - Loans | B15: INCL | C15: Financial asset information will be recorded using a journal voucher.
A16: =CONCATENATE('FFM-Functions-Activities'!B8,": ",'FFM-Functions-Activities'!D8) -> Financial Asset Information Management: Financial Asset Information Processing - Heritage Assets and Stewardship Land | B16: INCL | C16: Financial asset information will be recorded using a journal voucher.
A17: =CONCATENATE('FFM-Functions-Activities'!B9,": ",'FFM-Functions-Activities'!D9) -> Financial Asset Information Management: Financial Asset Information Processing - Federal Oil and Gas Resources | B17: INCL | C17: Financial asset information will be recorded using a journal voucher.
A18: =CONCATENATE('FFM-Functions-Activities'!B10,": ",'FFM-Functions-Activities'!D10) -> Financial Asset Information Management: Financial Asset Information Processing - Other Federal Assets | B18: INCL | C18: Financial asset information will be recorded using a journal voucher.
A19: =CONCATENATE('FFM-Functions-Activities'!B11,": ",'FFM-Functions-Activities'!D11) -> Financial Asset Information Management: Financial Asset Information Reporting | B19: INCL | C19: The required standard set of FM reports/information extracts are provided; agency-specific reports/information extracts can be developed and provided for an additional cost.
A20: =CONCATENATE('FFM-Functions-Activities'!B12,": ",'FFM-Functions-Activities'!D12) -> Payable Management: Payee Setup and Maintenance | B20: INCL | C20: The required standard BIE with SAM.gov is provided; agency-specific BIE extensions can be developed and provided for an additional cost.
A21: =CONCATENATE('FFM-Functions-Activities'!B13,": ",'FFM-Functions-Activities'!D13) -> Payable Management: Obligation Management | B21: INCL | C21: The required standard BIEs with other lines of business (Functional Areas) are provided; agency-specific BIE extensions can be developed and provided for an additional cost.
A22: =CONCATENATE('FFM-Functions-Activities'!B14,": ",'FFM-Functions-Activities'!D14) -> Payable Management: Payment Processing - Intragovernmental Payments | B22: INCL | C22: The required standard BIE with G-Invoicing is provided; agency-specific BIE extensions can be developed and provided for an additional cost.
A23: =CONCATENATE('FFM-Functions-Activities'!B15,": ",'FFM-Functions-Activities'!D15) -> Payable Management: Payment Processing - Payroll Payments | B23: INCL | C23: The required standard BIEs for payroll are provided; agency-specific BIE extensions can be developed and provided for an additional cost.
A24: =CONCATENATE('FFM-Functions-Activities'!B16,": ",'FFM-Functions-Activities'!D16) -> Payable Management: Payment Processing - Travel Temporary Duty (TDY) and Local Payments | B24: INCL | C24: The required standard BIE with the TRT Functional Area is provided; agency-specific BIE extensions can be developed and provided for an additional cost.
A25: =CONCATENATE('FFM-Functions-Activities'!B17,": ",'FFM-Functions-Activities'!D17) -> Payable Management: Payment Processing - Travel PCS Payments | B25: INCL
A26: =CONCATENATE('FFM-Functions-Activities'!B18,": ",'FFM-Functions-Activities'!D18) -> Payable Management: Payment Processing - Commercial Payments | B26: INCL | C26: The required standard BIE with the ACQ Functional Area is provided; agency-specific BIE extensions and additional BIEs can be developed and provided for an additional cost.
A27: =CONCATENATE('FFM-Functions-Activities'!B19,": ",'FFM-Functions-Activities'!D19) -> Payable Management: Payment Processing - Grant Payments | B27: INCL | C27: The required standard BIE with the GRM Functional Area is provided; agency-specific BIE extensions can be developed and provided for an additional cost.
A28: =CONCATENATE('FFM-Functions-Activities'!B20,": ",'FFM-Functions-Activities'!D20) -> Payable Management: Payment Processing - Loan Payments | B28: INCL
A29: =CONCATENATE('FFM-Functions-Activities'!B21,": ",'FFM-Functions-Activities'!D21) -> Payable Management: Payment Processing - Other Payments (Foreign and Miscellaneous Payments) | B29: INCL
A30: =CONCATENATE('FFM-Functions-Activities'!B22,": ",'FFM-Functions-Activities'!D22) -> Payable Management: Payment Disbursement | B30: INCL
A31: =CONCATENATE('FFM-Functions-Activities'!B23,": ",'FFM-Functions-Activities'!D23) -> Payable Management: Payment Confirmation and Issue Resolution | B31: INCL
A32: =CONCATENATE('FFM-Functions-Activities'!B24,": ",'FFM-Functions-Activities'!D24) -> Payable Management: Payment Reporting | B32: INCL | C32: The required standard set of FM reports/information extracts are provided; agency-specific reports/information extracts can be developed and provided for an additional cost.
A33: =CONCATENATE('FFM-Functions-Activities'!B25,": ",'FFM-Functions-Activities'!D25) -> Revenue Management: Revenue Processing | B33: INCL
A34: =CONCATENATE('FFM-Functions-Activities'!B26,": ",'FFM-Functions-Activities'!D26) -> Revenue Management: Revenue Reporting | B34: INCL | C34: A standard set of FM reports/information extracts are provided; agency-specific reports/information extracts can be developed and provided for an additional cost.
A35: =CONCATENATE('FFM-Functions-Activities'!B27,": ",'FFM-Functions-Activities'!D27) -> Reimbursable Management: Reimbursable Agreement Setup and Maintenance | B35: INCL
A36: =CONCATENATE('FFM-Functions-Activities'!B28,": ",'FFM-Functions-Activities'!D28) -> Reimbursable Management: Reimbursable Invoicing | B36: INCL | C36: The required standard BIE with G-Invoicing is provided; agency-specific BIE extensions can be developed and provided for an additional cost.
A37: =CONCATENATE('FFM-Functions-Activities'!B29,": ",'FFM-Functions-Activities'!D29) -> Reimbursable Management: Reimbursable Receipt Processing | B37: INCL | C37: The required standard BIE with G-Invoicing is provided; agency-specific BIE extensions can be developed and provided for an additional cost.
A38: =CONCATENATE('FFM-Functions-Activities'!B30,": ",'FFM-Functions-Activities'!D30) -> Reimbursable Management: Reimbursable Reconciliation | B38: INCL
A39: =CONCATENATE('FFM-Functions-Activities'!B31,": ",'FFM-Functions-Activities'!D31) -> Reimbursable Management: Reimbursable Closeout | B39: INCL
A40: =CONCATENATE('FFM-Functions-Activities'!B32,": ",'FFM-Functions-Activities'!D32) -> Reimbursable Management: Reimbursable Reporting | B40: INCL | C40: A standard set of FM reports/information extracts are provided; agency-specific reports/information extracts can be developed and provided for an additional cost.
A41: =CONCATENATE('FFM-Functions-Activities'!B33,": ",'FFM-Functions-Activities'!D33) -> Receivable and Collection Management: Payer Setup and Maintenance | B41: INCL
A42: =CONCATENATE('FFM-Functions-Activities'!B34,": ",'FFM-Functions-Activities'!D34) -> Receivable and Collection Management: Public Receivable Setup and Billing Invoicing | B42: INCL
A43: =CONCATENATE('FFM-Functions-Activities'!B35,": ",'FFM-Functions-Activities'!D35) -> Receivable and Collection Management: Public Receipt Processing | B43: INCL
A44: =CONCATENATE('FFM-Functions-Activities'!B36,": ",'FFM-Functions-Activities'!D36) -> Receivable and Collection Management: Credit Memo and Adjustment Processing | B44: INCL
A45: =CONCATENATE('FFM-Functions-Activities'!B37,": ",'FFM-Functions-Activities'!D37) -> Receivable and Collection Management: Public Receivable Monitoring and Maintenance | B45: INCL
A46: =CONCATENATE('FFM-Functions-Activities'!B38,": ",'FFM-Functions-Activities'!D38) -> Receivable and Collection Management: Public Receivable and Collection Reporting | B46: INCL | C46: The required standard set of FM reports/information extracts are provided; agency-specific reports/information extracts can be developed and provided for an additional cost.
A47: =CONCATENATE('FFM-Functions-Activities'!B39,": ",'FFM-Functions-Activities'!D39) -> Delinquent Debt Management: Delinquent Debt Collection | B47: INCL
A48: =CONCATENATE('FFM-Functions-Activities'!B40,": ",'FFM-Functions-Activities'!D40) -> Delinquent Debt Management: Delinquent Debt Write-off and Closeout | B48: INCL
A49: =CONCATENATE('FFM-Functions-Activities'!B41,": ",'FFM-Functions-Activities'!D41) -> Delinquent Debt Management: Delinquent Debt Reporting | B49: INCL | C49: The required standard set of FM reports/information extracts are provided; agency-specific reports/information extracts can be developed and provided for an additional cost.
A50: =CONCATENATE('FFM-Functions-Activities'!B42,": ",'FFM-Functions-Activities'!D42) -> Cost Management: Cost Management Setup and Maintenance | B50: INCL
A51: =CONCATENATE('FFM-Functions-Activities'!B43,": ",'FFM-Functions-Activities'!D43) -> Cost Management: Cost Accumulation and Allocation | B51: INCL
A52: =CONCATENATE('FFM-Functions-Activities'!B44,": ",'FFM-Functions-Activities'!D44) -> Cost Management: Cost Reporting | B52: INCL | C52: A standard set of FM reports/information extracts are provided; agency-specific reports/information extracts can be developed and provided for an additional cost.
A53: =CONCATENATE('FFM-Functions-Activities'!B45,": ",'FFM-Functions-Activities'!D45) -> General Ledger Management: General Ledger Setup and Maintenance | B53: INCL
A54: =CONCATENATE('FFM-Functions-Activities'!B46,": ",'FFM-Functions-Activities'!D46) -> General Ledger Management: General Ledger Posting | B54: INCL
A55: =CONCATENATE('FFM-Functions-Activities'!B47,": ",'FFM-Functions-Activities'!D47) -> General Ledger Management: Accrual and Liability/Asset Processing | B55: INCL | C55: Liability/asset information will be recorded using a journal voucher.
A56: =CONCATENATE('FFM-Functions-Activities'!B48,": ",'FFM-Functions-Activities'!D48) -> General Ledger Management: Period End Closing | B56: INCL
A57: =CONCATENATE('FFM-Functions-Activities'!B49,": ",'FFM-Functions-Activities'!D49) -> Financial Reconciliation: Reconciliation of General Ledger and Subledgers | B57: INCL
A58: =CONCATENATE('FFM-Functions-Activities'!B50,": ",'FFM-Functions-Activities'!D50) -> Financial Reconciliation: Reconciliation of Intragovernmental Activity | B58: INCL
A59: =CONCATENATE('FFM-Functions-Activities'!B51,": ",'FFM-Functions-Activities'!D51) -> Financial Reconciliation: Reconciliation with Treasury Balance | B59: INCL
A60: =CONCATENATE('FFM-Functions-Activities'!B52,": ",'FFM-Functions-Activities'!D52) -> Financial / Performance Reporting: Treasury Reporting | B60: INCL | C60: The required standard set of FM reports/information extracts are provided; agency-specific reports/information extracts can be developed and provided for an additional cost.
A61: =CONCATENATE('FFM-Functions-Activities'!B53,": ",'FFM-Functions-Activities'!D53) -> Financial / Performance Reporting: Financial Statement Preparation | B61: INCL | C61: The required standard set of FM reports/information extracts are provided; agency-specific reports/information extracts can be developed and provided for an additional cost.
A62: =CONCATENATE('FFM-Functions-Activities'!B54,": ",'FFM-Functions-Activities'!D54) -> Financial / Performance Reporting: Cash Forecasting and Reporting | B62: INCL | C62: A standard set of FM reports/information extracts are provided; agency-specific reports/information extracts can be developed and provided for an additional cost.
A63: =CONCATENATE('FFM-Functions-Activities'!B55,": ",'FFM-Functions-Activities'!D55) -> Financial / Performance Reporting: Financial Performance and Operational Reporting | B63: INCL | C63: A standard set of FM reports/information extracts are provided; agency-specific reports/information extracts can be developed and provided for an additional cost.
A64: =CONCATENATE('FFM-Functions-Activities'!B56,": ",'FFM-Functions-Activities'!D56) -> Financial / Performance Reporting: Internal Control/Compliance Reviews | B64: INCL | C64: A standard set of FM reports/information extracts are provided; agency-specific reports/information extracts can be developed and provided for an additional cost.
A66: Asset View
A67: Service Delivery Resources: | B67: Technology | H67: Workforce | J67: Advisory | L67: Additional Explanation
A68: Cost Pools: | B68: Facilities | C68: Telecom-Network | D68: Hardware | E68: Software | F68: Internal Services | G68: Outside Services | H68: Internal Labor | I68: External Labor | J68: Internal Labor | K68: External Labor
A69: Service Delivery Layers and Towers: Sub-Towers
A70: SL0: Service Delivery Management
A71: IT Management: IT Management and Strategic Planning | B71: N/A | C71: N/A | D71: N/A | E71: N/A | F71: N/A | G71: INCL | H71: INCL | I71: INCL | J71: N/A | K71: INCL | L71: Outside (sub) services include xxxxxx SaaS
A72: IT Management: Enterprise Architecture | B72: N/A | C72: N/A | D72: N/A | E72: N/A | F72: N/A | G72: INCL | H72: INCL | I72: INCL | J72: N/A | K72: INCL | L72: Outside (sub) services include xxxxxx SaaS
A73: IT Management: IT Finance | B73: N/A | C73: N/A | D73: N/A | E73: N/A | F73: INCL | G73: N/A | H73: INCL | I73: N/A | J73: N/A | K73: N/A
A74: IT Management: IT Vendor Management | B74: N/A | C74: N/A | D74: N/A | E74: N/A | F74: INCL | G74: N/A | H74: INCL | I74: N/A | J74: N/A | K74: N/A
A75: IT Management: IT Human Capital Management | B75: N/A | C75: N/A | D75: N/A | E75: N/A | F75: INCL | G75: N/A | H75: INCL | I75: N/A | J75: N/A | K75: N/A
A76: IT Management: IT Personnel Travel | B76: N/A | C76: N/A | D76: N/A | E76: N/A | F76: INCL | G76: N/A | H76: INCL | I76: N/A | J76: N/A | K76: N/A
A77: Delivery: IT Service Management | B77: N/A | C77: N/A | D77: N/A | E77: N/A | F77: N/A | G77: INCL | H77: INCL | I77: INCL | J77: N/A | K77: INCL | L77: Outside (sub) services include xxxxxx SaaS
A78: Delivery: Program, Product & Project Management | B78: N/A | C78: N/A | D78: N/A | E78: N/A | F78: N/A | G78: INCL | H78: INCL | I78: INCL | J78: N/A | K78: N/A | L78: Outside (sub) services include xxxxxx SaaS and Microsoft Cloud Services (MSProject)
A79: Delivery: Client Management | B79: N/A | C79: N/A | D79: N/A | E79: N/A | F79: N/A | G79: INCL | H79: INCL | I79: INCL | J79: N/A | K79: N/A | L79: Outside (sub) services include xxxxxx SaaS
A80: Delivery: Operations Center | B80: N/A | C80: N/A | D80: N/A | E80: N/A | F80: N/A | G80: INCL | H80: INCL | I80: INCL | J80: N/A | K80: N/A | L80: Outside (sub) services include xxxxxx SaaS
A81: Delivery: IT Service Design and Improvement | B81: N/A | C81: N/A | D81: N/A | E81: N/A | F81: N/A | G81: INCL | H81: INCL | I81: INCL | J81: N/A | K81: N/A | L81: Outside (sub) services include xxxxxx SaaS
A82: Security & Compliance: Security | B82: N/A | C82: N/A | D82: N/A | E82: INCL | F82: N/A | G82: N/A | H82: INCL | I82: INCL | J82: N/A | K82: INCL
A83: Security & Compliance: Compliance | B83: N/A | C83: N/A | D83: N/A | E83: INCL | F83: N/A | G83: N/A | H83: INCL | I83: INCL | J83: N/A | K83: INCL
A84: Security & Compliance: Disaster Recovery | B84: N/A | C84: N/A | D84: N/A | E84: INCL | F84: N/A | G84: N/A | H84: INCL | I84: INCL | J84: N/A | K84: INCL
A85: Security & Compliance: Federal Records Mgmt | B85: N/A | C85: N/A | D85: N/A | E85: INCL | F85: N/A | G85: N/A | H85: INCL | I85: INCL | J85: N/A | K85: INCL
A86: Business Delivery Mgmt & Support: Business Program, Product & Project Mgmt | B86: N/A | C86: N/A | D86: N/A | E86: N/A | F86: N/A | G86: N/A | H86: N/A | I86: N/A | J86: N/A | K86: N/A
A87: Compliance & Controls: Continuity of Operations (COOP) | B87: N/A | C87: N/A | D87: N/A | E87: N/A | F87: N/A | G87: N/A | H87: N/A | I87: N/A | J87: EXCL/O | K87: N/A | L87: COOP advisory services can be included in service scope for an additional cost
A88: Business Management: Business Management & Strategic Planning | B88: N/A | C88: N/A | D88: N/A | E88: N/A | F88: N/A | G88: N/A | H88: N/A | I88: N/A | J88: N/A | K88: N/A
A89: Business Management: Business Finance | B89: N/A | C89: N/A | D89: N/A | E89: INCL | F89: N/A | G89: N/A | H89: N/A | I89: N/A | J89: N/A | K89: N/A
A90: Business Management: Business Vendor Management | B90: N/A | C90: N/A | D90: N/A | E90: INCL | F90: N/A | G90: N/A | H90: N/A | I90: N/A | J90: N/A | K90: N/A
A91: Business Management: Business Human Capital Management | B91: N/A | C91: N/A | D91: N/A | E91: INCL | F91: N/A | G91: N/A | H91: N/A | I91: N/A | J91: N/A | K91: N/A
A92: Business Management: Business Personnel Travel | B92: N/A | C92: N/A | D92: N/A | E92: INCL | F92: N/A | G92: N/A | H92: N/A | I92: N/A | J92: N/A | K92: N/A
A93: SL1: Facilities and Telecommunications
A94: Data Center: Enterprise Data Center | B94: N/A | C94: N/A | D94: N/A | E94: N/A | F94: N/A | G94: INCL | H94: N/A | I94: N/A | J94: N/A | K94: N/A | L94: Outside (sub) services include IaaS
A95: Data Center: Other IT Facilities | B95: INCL | C95: N/A | D95: N/A | E95: N/A | F95: N/A | G95: N/A | H95: N/A | I95: N/A | J95: N/A | K95: N/A
A96: Data Center: IT Transport Vehicles & Equipment | B96: INCL | C96: N/A | D96: N/A | E96: N/A | F96: N/A | G96: N/A | H96: N/A | I96: N/A | J96: N/A | K96: N/A | L96: Provided for Service Provider staff only
A97: Data Center: IT Office Furniture & Supplies | B97: INCL | C97: N/A | D97: N/A | E97: N/A | F97: N/A | G97: N/A | H97: N/A | I97: N/A | J97: N/A | K97: N/A | L97: Provided for Service Provider staff only
A98: Business Facilities, Equipment & Supplies: Business Facilities | B98: N/A | C98: N/A | D98: N/A | E98: N/A | F98: N/A | G98: N/A | H98: N/A | I98: N/A | J98: N/A | K98: N/A
A99: Business Facilities, Equipment & Supplies: Business Transport Vehicles & Equipment | B99: N/A | C99: N/A | D99: N/A | E99: N/A | F99: N/A | G99: N/A | H99: N/A | I99: N/A | J99: N/A | K99: N/A
A100: Business Facilities, Equipment & Supplies: Business Office Furniture & Supplies | B100: N/A | C100: N/A | D100: N/A | E100: N/A | F100: N/A | G100: N/A | H100: N/A | I100: N/A | J100: N/A | K100: N/A
A101: Network: LAN/WAN | B101: N/A | C101: PRTL/R* | D101: PRTL/R* | E101: PRTL/R* | F101: N/A | G101: N/A | H101: PRTL/R* | I101: PRTL/R* | J101: N/A | K101: N/A | L101: Network connectivity outside of the Service Provider firewall/perimeter is the responsibility of the Service Customer.
A102: Network: Voice | B102: N/A | C102: N/A | D102: N/A | E102: N/A | F102: N/A | G102: N/A | H102: N/A | I102: N/A | J102: N/A | K102: N/A
...

Sheet FM Sol-Serv Def Example - PaaS
B1: Draft/Pre-Decisional
B2: This RFI (Request for Information) is issued solely for market research and planning purposes. The RFI does not constitute a solicitation or a commitment to a particular acquisition strategy. The RFI is intended to get industry feedback on the vision for the FM QSMO Marketplace, which includes core financial system and other financial management services and solutions. Nothing in this document should be construed as a final government decision upon which industry should take action and the RFI is subject to change. Treasury is not seeking proposals at this time and will not consider unsolicited proposals provided in response to the RFI. All information received in response to the RFI that is marked as proprietary will be handled accordingly. Responses to this notice are not offers and cannot be accepted by the Government to form a binding contract. Responders are solely responsible for all expenses associated with responding to the RFI.
A3: FM Solution/Service Definition Example - Core FS PaaS
A4: ='Cover Page'!A16 -> As of: May 26, 2021
A6: Provider Name: | B6: XYZ Company
A7: FM Solution/Service Package Name: | B7: XYZ Core FS Platform-as-a-Service (PaaS)
A8: FM Solution/Service Package Short Description: | B8: XYZ Core FS PaaS offers capabilities that enable customers to perform all FIBF FFM Functions and is fully compliant with Core FS Baseline Solution standards.
A9: Business View
A10: FFM Functions: Activities | B10: Indicator | C10: Additional Explanation
A11: =CONCATENATE('FFM-Functions-Activities'!B3,": ",'FFM-Functions-Activities'!D3) -> Budget Execution: Budget Setup and Maintenance | B11: INCL
A12: =CONCATENATE('FFM-Functions-Activities'!B4,": ",'FFM-Functions-Activities'!D4) -> Budget Execution: Fund Allocation and Control | B12: INCL | C12: The required standard BIE with other lines of business (Functional Areas) is provided to automate execution of funds availability checks
A13: =CONCATENATE('FFM-Functions-Activities'!B5,": ",'FFM-Functions-Activities'!D5) -> Budget Execution: Budgetary Reporting | B13: INCL | C13: The required standard set of FM reports/information extracts are provided
A14: =CONCATENATE('FFM-Functions-Activities'!B6,": ",'FFM-Functions-Activities'!D6) -> Financial Asset Information Management: Financial Asset Information Processing - Property, Plant, and Equipment | B14: INCL | C14: Financial asset information will be recorded using a journal voucher.
A15: =CONCATENATE('FFM-Functions-Activities'!B7,": ",'FFM-Functions-Activities'!D7) -> Financial Asset Information Management: Financial Asset Information Processing - Loans | B15: INCL | C15: Financial asset information will be recorded using a journal voucher.
A16: =CONCATENATE('FFM-Functions-Activities'!B8,": ",'FFM-Functions-Activities'!D8) -> Financial Asset Information Management: Financial Asset Information Processing - Heritage Assets and Stewardship Land | B16: INCL | C16: Financial asset information will be recorded using a journal voucher.
A17: =CONCATENATE('FFM-Functions-Activities'!B9,": ",'FFM-Functions-Activities'!D9) -> Financial Asset Information Management: Financial Asset Information Processing - Federal Oil and Gas Resources | B17: INCL | C17: Financial asset information will be recorded using a journal voucher.
A18: =CONCATENATE('FFM-Functions-Activities'!B10,": ",'FFM-Functions-Activities'!D10) -> Financial Asset Information Management: Financial Asset Information Processing - Other Federal Assets | B18: INCL | C18: Financial asset information will be recorded using a journal voucher.
A19: =CONCATENATE('FFM-Functions-Activities'!B11,": ",'FFM-Functions-Activities'!D11) -> Financial Asset Information Management: Financial Asset Information Reporting | B19: INCL | C19: The required standard set of FM reports/information extracts are provided
A20: =CONCATENATE('FFM-Functions-Activities'!B12,": ",'FFM-Functions-Activities'!D12) -> Payable Management: Payee Setup and Maintenance | B20: INCL | C20: The required standard BIE with SAM.gov is provided
A21: =CONCATENATE('FFM-Functions-Activities'!B13,": ",'FFM-Functions-Activities'!D13) -> Payable Management: Obligation Management | B21: INCL | C21: The required standard BIEs with other lines of business (Functional Areas) are provided.
A22: =CONCATENATE('FFM-Functions-Activities'!B14,": ",'FFM-Functions-Activities'!D14) -> Payable Management: Payment Processing - Intragovernmental Payments | B22: INCL | C22: The required standard BIE with G-Invoicing is provided.
A23: =CONCATENATE('FFM-Functions-Activities'!B15,": ",'FFM-Functions-Activities'!D15) -> Payable Management: Payment Processing - Payroll Payments | B23: INCL | C23: The required standard BIEs for payroll are provided.
A24: =CONCATENATE('FFM-Functions-Activities'!B16,": ",'FFM-Functions-Activities'!D16) -> Payable Management: Payment Processing - Travel Temporary Duty (TDY) and Local Payments | B24: INCL | C24: The required standard BIE with the TRT Functional Area is provided.
A25: =CONCATENATE('FFM-Functions-Activities'!B17,": ",'FFM-Functions-Activities'!D17) -> Payable Management: Payment Processing - Travel PCS Payments | B25: INCL
A26: =CONCATENATE('FFM-Functions-Activities'!B18,": ",'FFM-Functions-Activities'!D18) -> Payable Management: Payment Processing - Commercial Payments | B26: INCL | C26: The required standard BIE with the ACQ Functional Area is provided.
A27: =CONCATENATE('FFM-Functions-Activities'!B19,": ",'FFM-Functions-Activities'!D19) -> Payable Management: Payment Processing - Grant Payments | B27: INCL | C27: The required standard BIE with the GRM Functional Area is provided.
A28: =CONCATENATE('FFM-Functions-Activities'!B20,": ",'FFM-Functions-Activities'!D20) -> Payable Management: Payment Processing - Loan Payments | B28: INCL
A29: =CONCATENATE('FFM-Functions-Activities'!B21,": ",'FFM-Functions-Activities'!D21) -> Payable Management: Payment Processing - Other Payments (Foreign and Miscellaneous Payments) | B29: INCL
A30: =CONCATENATE('FFM-Functions-Activities'!B22,": ",'FFM-Functions-Activities'!D22) -> Payable Management: Payment Disbursement | B30: INCL
A31: =CONCATENATE('FFM-Functions-Activities'!B23,": ",'FFM-Functions-Activities'!D23) -> Payable Management: Payment Confirmation and Issue Resolution | B31: INCL
A32: =CONCATENATE('FFM-Functions-Activities'!B24,": ",'FFM-Functions-Activities'!D24) -> Payable Management: Payment Reporting | B32: INCL | C32: The required standard set of FM reports/information extracts are provided.
A33: =CONCATENATE('FFM-Functions-Activities'!B25,": ",'FFM-Functions-Activities'!D25) -> Revenue Management: Revenue Processing | B33: INCL
A34: =CONCATENATE('FFM-Functions-Activities'!B26,": ",'FFM-Functions-Activities'!D26) -> Revenue Management: Revenue Reporting | B34: INCL | C34: A standard set of FM reports/information extracts are provided.
A35: =CONCATENATE('FFM-Functions-Activities'!B27,": ",'FFM-Functions-Activities'!D27) -> Reimbursable Management: Reimbursable Agreement Setup and Maintenance | B35: INCL
A36: =CONCATENATE('FFM-Functions-Activities'!B28,": ",'FFM-Functions-Activities'!D28) -> Reimbursable Management: Reimbursable Invoicing | B36: INCL | C36: The required standard BIE with G-Invoicing is provided.
A37: =CONCATENATE('FFM-Functions-Activities'!B29,": ",'FFM-Functions-Activities'!D29) -> Reimbursable Management: Reimbursable Receipt Processing | B37: INCL | C37: The required standard BIE with G-Invoicing is provided.
A38: =CONCATENATE('FFM-Functions-Activities'!B30,": ",'FFM-Functions-Activities'!D30) -> Reimbursable Management: Reimbursable Reconciliation | B38: INCL
A39: =CONCATENATE('FFM-Functions-Activities'!B31,": ",'FFM-Functions-Activities'!D31) -> Reimbursable Management: Reimbursable Closeout | B39: INCL
A40: =CONCATENATE('FFM-Functions-Activities'!B32,": ",'FFM-Functions-Activities'!D32) -> Reimbursable Management: Reimbursable Reporting | B40: INCL | C40: A standard set of FM reports/information extracts are provided.
A41: =CONCATENATE('FFM-Functions-Activities'!B33,": ",'FFM-Functions-Activities'!D33) -> Receivable and Collection Management: Payer Setup and Maintenance | B41: INCL
A42: =CONCATENATE('FFM-Functions-Activities'!B34,": ",'FFM-Functions-Activities'!D34) -> Receivable and Collection Management: Public Receivable Setup and Billing Invoicing | B42: INCL
A43: =CONCATENATE('FFM-Functions-Activities'!B35,": ",'FFM-Functions-Activities'!D35) -> Receivable and Collection Management: Public Receipt Processing | B43: INCL
A44: =CONCATENATE('FFM-Functions-Activities'!B36,": ",'FFM-Functions-Activities'!D36) -> Receivable and Collection Management: Credit Memo and Adjustment Processing | B44: INCL
A45: =CONCATENATE('FFM-Functions-Activities'!B37,": ",'FFM-Functions-Activities'!D37) -> Receivable and Collection Management: Public Receivable Monitoring and Maintenance | B45: INCL
A46: =CONCATENATE('FFM-Functions-Activities'!B38,": ",'FFM-Functions-Activities'!D38) -> Receivable and Collection Management: Public Receivable and Collection Reporting | B46: INCL | C46: The required standard set of FM reports/information extracts are provided.
A47: =CONCATENATE('FFM-Functions-Activities'!B39,": ",'FFM-Functions-Activities'!D39) -> Delinquent Debt Management: Delinquent Debt Collection | B47: INCL
A48: =CONCATENATE('FFM-Functions-Activities'!B40,": ",'FFM-Functions-Activities'!D40) -> Delinquent Debt Management: Delinquent Debt Write-off and Closeout | B48: INCL
A49: =CONCATENATE('FFM-Functions-Activities'!B41,": ",'FFM-Functions-Activities'!D41) -> Delinquent Debt Management: Delinquent Debt Reporting | B49: INCL | C49: The required standard set of FM reports/information extracts are provided.
A50: =CONCATENATE('FFM-Functions-Activities'!B42,": ",'FFM-Functions-Activities'!D42) -> Cost Management: Cost Management Setup and Maintenance | B50: INCL
A51: =CONCATENATE('FFM-Functions-Activities'!B43,": ",'FFM-Functions-Activities'!D43) -> Cost Management: Cost Accumulation and Allocation | B51: INCL
A52: =CONCATENATE('FFM-Functions-Activities'!B44,": ",'FFM-Functions-Activities'!D44) -> Cost Management: Cost Reporting | B52: INCL | C52: A standard set of FM reports/information extracts are provided.
A53: =CONCATENATE('FFM-Functions-Activities'!B45,": ",'FFM-Functions-Activities'!D45) -> General Ledger Management: General Ledger Setup and Maintenance | B53: INCL
A54: =CONCATENATE('FFM-Functions-Activities'!B46,": ",'FFM-Functions-Activities'!D46) -> General Ledger Management: General Ledger Posting | B54: INCL
A55: =CONCATENATE('FFM-Functions-Activities'!B47,": ",'FFM-Functions-Activities'!D47) -> General Ledger Management: Accrual and Liability/Asset Processing | B55: INCL | C55: Liability/asset information will be recorded using a journal voucher.
A56: =CONCATENATE('FFM-Functions-Activities'!B48,": ",'FFM-Functions-Activities'!D48) -> General Ledger Management: Period End Closing | B56: INCL
A57: =CONCATENATE('FFM-Functions-Activities'!B49,": ",'FFM-Functions-Activities'!D49) -> Financial Reconciliation: Reconciliation of General Ledger and Subledgers | B57: INCL
A58: =CONCATENATE('FFM-Functions-Activities'!B50,": ",'FFM-Functions-Activities'!D50) -> Financial Reconciliation: Reconciliation of Intragovernmental Activity | B58: INCL
A59: =CONCATENATE('FFM-Functions-Activities'!B51,": ",'FFM-Functions-Activities'!D51) -> Financial Reconciliation: Reconciliation with Treasury Balance | B59: INCL
A60: =CONCATENATE('FFM-Functions-Activities'!B52,": ",'FFM-Functions-Activities'!D52) -> Financial / Performance Reporting: Treasury Reporting | B60: INCL | C60: The required standard set of FM reports/information extracts are provided.
A61: =CONCATENATE('FFM-Functions-Activities'!B53,": ",'FFM-Functions-Activities'!D53) -> Financial / Performance Reporting: Financial Statement Preparation | B61: INCL | C61: The required standard set of FM reports/information extracts are provided.
A62: =CONCATENATE('FFM-Functions-Activities'!B54,": ",'FFM-Functions-Activities'!D54) -> Financial / Performance Reporting: Cash Forecasting and Reporting | B62: INCL | C62: A standard set of FM reports/information extracts are provided.
A63: =CONCATENATE('FFM-Functions-Activities'!B55,": ",'FFM-Functions-Activities'!D55) -> Financial / Performance Reporting: Financial Performance and Operational Reporting | B63: INCL | C63: A standard set of FM reports/information extracts are provided.
A64: =CONCATENATE('FFM-Functions-Activities'!B56,": ",'FFM-Functions-Activities'!D56) -> Financial / Performance Reporting: Internal Control/Compliance Reviews | B64: INCL | C64: A standard set of FM reports/information extracts are provided.
A66: Asset View
A67: Service Delivery Resources: | B67: Technology | H67: Workforce | J67: Advisory | L67: Additional Explanation
A68: Cost Pools: | B68: Facilities | C68: Telecom-Network | D68: Hardware | E68: Software | F68: Internal Services | G68: Outside Services | H68: Internal Labor | I68: External Labor | J68: Internal Labor | K68: External Labor
A69: Service Delivery Layers and Towers: Sub-Towers
A70: SL0: Service Delivery Management
A71: IT Management: IT Management and Strategic Planning | B71: N/A | C71: N/A | D71: N/A | E71: N/A | F71: N/A | G71: INCL | H71: INCL | I71: INCL | J71: N/A | K71: INCL | L71: Outside (sub) services include xxxxxx SaaS
A72: IT Management: Enterprise Architecture | B72: N/A | C72: N/A | D72: N/A | E72: N/A | F72: N/A | G72: INCL | H72: INCL | I72: INCL | J72: N/A | K72: INCL | L72: Outside (sub) services include xxxxxx SaaS
A73: IT Management: IT Finance | B73: N/A | C73: N/A | D73: N/A | E73: N/A | F73: INCL | G73: N/A | H73: INCL | I73: N/A | J73: N/A | K73: N/A
A74: IT Management: IT Vendor Management | B74: N/A | C74: N/A | D74: N/A | E74: N/A | F74: INCL | G74: N/A | H74: INCL | I74: N/A | J74: N/A | K74: N/A
A75: IT Management: IT Human Capital Management | B75: N/A | C75: N/A | D75: N/A | E75: N/A | F75: INCL | G75: N/A | H75: INCL | I75: N/A | J75: N/A | K75: N/A
A76: IT Management: IT Personnel Travel | B76: N/A | C76: N/A | D76: N/A | E76: N/A | F76: INCL | G76: N/A | H76: INCL | I76: N/A | J76: N/A | K76: N/A
A77: Delivery: IT Service Management | B77: N/A | C77: N/A | D77: N/A | E77: N/A | F77: N/A | G77: INCL | H77: INCL | I77: INCL | J77: N/A | K77: INCL | L77: Outside (sub) services include xxxxxx SaaS
A78: Delivery: Program, Product & Project Management | B78: N/A | C78: N/A | D78: N/A | E78: N/A | F78: N/A | G78: INCL | H78: INCL | I78: INCL | J78: N/A | K78: N/A | L78: Outside (sub) services include xxxxxx SaaS and Microsoft Cloud Services (MSProject)
A79: Delivery: Client Management | B79: N/A | C79: N/A | D79: N/A | E79: N/A | F79: N/A | G79: INCL | H79: INCL | I79: INCL | J79: N/A | K79: N/A | L79: Outside (sub) services include xxxxxx SaaS
A80: Delivery: Operations Center | B80: N/A | C80: N/A | D80: N/A | E80: N/A | F80: N/A | G80: INCL | H80: INCL | I80: INCL | J80: N/A | K80: N/A | L80: Outside (sub) services include xxxxxx SaaS
A81: Delivery: IT Service Design and Improvement | B81: N/A | C81: N/A | D81: N/A | E81: N/A | F81: N/A | G81: INCL | H81: INCL | I81: INCL | J81: N/A | K81: N/A | L81: Outside (sub) services include xxxxxx SaaS
A82: Security & Compliance: Security | B82: N/A | C82: N/A | D82: N/A | E82: INCL | F82: N/A | G82: N/A | H82: INCL | I82: INCL | J82: N/A | K82: INCL
A83: Security & Compliance: Compliance | B83: N/A | C83: N/A | D83: N/A | E83: INCL | F83: N/A | G83: N/A | H83: INCL | I83: INCL | J83: N/A | K83: INCL
A84: Security & Compliance: Disaster Recovery | B84: N/A | C84: N/A | D84: N/A | E84: INCL | F84: N/A | G84: N/A | H84: INCL | I84: INCL | J84: N/A | K84: INCL
A85: Security & Compliance: Federal Records Mgmt | B85: N/A | C85: N/A | D85: N/A | E85: INCL | F85: N/A | G85: N/A | H85: INCL | I85: INCL | J85: N/A | K85: INCL
A86: Business Delivery Mgmt & Support: Business Program, Product & Project Mgmt | B86: N/A | C86: N/A | D86: N/A | E86: N/A | F86: N/A | G86: N/A | H86: N/A | I86: N/A | J86: N/A | K86: N/A
A87: Compliance & Controls: Continuity of Operations (COOP) | B87: N/A | C87: N/A | D87: N/A | E87: N/A | F87: N/A | G87: N/A | H87: N/A | I87: N/A | J87: N/A | K87: N/A
A88: Business Management: Business Management & Strategic Planning | B88: N/A | C88: N/A | D88: N/A | E88: N/A | F88: N/A | G88: N/A | H88: N/A | I88: N/A | J88: N/A | K88: N/A
A89: Business Management: Business Finance | B89: N/A | C89: N/A | D89: N/A | E89: INCL | F89: N/A | G89: N/A | H89: N/A | I89: N/A | J89: N/A | K89: N/A
A90: Business Management: Business Vendor Management | B90: N/A | C90: N/A | D90: N/A | E90: INCL | F90: N/A | G90: N/A | H90: N/A | I90: N/A | J90: N/A | K90: N/A
A91: Business Management: Business Human Capital Management | B91: N/A | C91: N/A | D91: N/A | E91: INCL | F91: N/A | G91: N/A | H91: N/A | I91: N/A | J91: N/A | K91: N/A
A92: Business Management: Business Personnel Travel | B92: N/A | C92: N/A | D92: N/A | E92: INCL | F92: N/A | G92: N/A | H92: N/A | I92: N/A | J92: N/A | K92: N/A
A93: SL1: Facilities and Telecommunications
A94: Data Center: Enterprise Data Center | B94: N/A | C94: N/A | D94: N/A | E94: N/A | F94: N/A | G94: INCL | H94: N/A | I94: N/A | J94: N/A | K94: N/A | L94: Outside (sub) services include IaaS
A95: Data Center: Other IT Facilities | B95: INCL | C95: N/A | D95: N/A | E95: N/A | F95: N/A | G95: N/A | H95: N/A | I95: N/A | J95: N/A | K95: N/A
A96: Data Center: IT Transport Vehicles & Equipment | B96: INCL | C96: N/A | D96: N/A | E96: N/A | F96: N/A | G96: N/A | H96: N/A | I96: N/A | J96: N/A | K96: N/A | L96: Provided for Service Provider staff only
A97: Data Center: IT Office Furniture & Supplies | B97: INCL | C97: N/A | D97: N/A | E97: N/A | F97: N/A | G97: N/A | H97: N/A | I97: N/A | J97: N/A | K97: N/A | L97: Provided for Service Provider staff only
A98: Business Facilities, Equipment & Supplies: Business Facilities | B98: N/A | C98: N/A | D98: N/A | E98: N/A | F98: N/A | G98: N/A | H98: N/A | I98: N/A | J98: N/A | K98: N/A
A99: Business Facilities, Equipment & Supplies: Business Transport Vehicles & Equipment | B99: N/A | C99: N/A | D99: N/A | E99: N/A | F99: N/A | G99: N/A | H99: N/A | I99: N/A | J99: N/A | K99: N/A
A100: Business Facilities, Equipment & Supplies: Business Office Furniture & Supplies | B100: N/A | C100: N/A | D100: N/A | E100: N/A | F100: N/A | G100: N/A | H100: N/A | I100: N/A | J100: N/A | K100: N/A
A101: Network: LAN/WAN | B101: N/A | C101: PRTL/R* | D101: PRTL/R* | E101: PRTL/R* | F101: N/A | G101: N/A | H101: PRTL/R* | I101: PRTL/R* | J101: N/A | K101: N/A | L101: Network connectivity outside of the Service Provider firewall/perimeter is the responsibility of the Service Customer.
A102: Network: Voice | B102: N/A | C102: N/A | D102: N/A | E102: N/A | F102: N/A | G102: N/A | H102: N/A | I102: N/A | J102: N/A | K102: N/A
...

Sheet FM Sol-Serv Def Example-Audit
B1: Draft/Pre-Decisional
B2: This RFI (Request for Information) is issued solely for market research and planning purposes. The RFI does not constitute a solicitation or a commitment to a particular acquisition strategy. The RFI is intended to get industry feedback on the vision for the FM QSMO Marketplace, which includes core financial system and other financial management services and solutions. Nothing in this document should be construed as a final government decision upon which industry should take action and the RFI is subject to change. Treasury is not seeking proposals at this time and will not consider unsolicited proposals provided in response to the RFI. All information received in response to the RFI that is marked as proprietary will be handled accordingly. Responses to this notice are not offers and cannot be accepted by the Government to form a binding contract. Responders are solely responsible for all expenses associated with responding to the RFI.
A3: FM Solution/Service Definition Example - Audit Services
A4: ='Cover Page'!A16 -> As of: May 26, 2021
A6: Provider Name: | B6: GHI Company
A7: FM Solution/Service Package Name: | B7: GHI Audit Support and Internal Control Review Services
A8: FM Solution/Service Package Short Description: | B8: GHI offers audit readiness and internal control review services for Federal financial management operations and Core FS solutions. Our services include personnel specializing in Federal financial management and software to plan, monitor, and report audit readiness and internal control review activities, schedules, issues, and resolution status.
A9: Business View
A10: FFM Functions: Activities | B10: Indicator | C10: Additional Explanation
A11: =CONCATENATE('FFM-Functions-Activities'!B3,": ",'FFM-Functions-Activities'!D3) -> Budget Execution: Budget Setup and Maintenance | B11: INCL | C11: Included in scope of review
A12: =CONCATENATE('FFM-Functions-Activities'!B4,": ",'FFM-Functions-Activities'!D4) -> Budget Execution: Fund Allocation and Control | B12: INCL | C12: Included in scope of review
A13: =CONCATENATE('FFM-Functions-Activities'!B5,": ",'FFM-Functions-Activities'!D5) -> Budget Execution: Budgetary Reporting | B13: INCL | C13: Included in scope of review
A14: =CONCATENATE('FFM-Functions-Activities'!B6,": ",'FFM-Functions-Activities'!D6) -> Financial Asset Information Management: Financial Asset Information Processing - Property, Plant, and Equipment | B14: INCL | C14: Included in scope of review
A15: =CONCATENATE('FFM-Functions-Activities'!B7,": ",'FFM-Functions-Activities'!D7) -> Financial Asset Information Management: Financial Asset Information Processing - Loans | B15: EXCL/O | C15: Can be included in service scope for additional cost
A16: =CONCATENATE('FFM-Functions-Activities'!B8,": ",'FFM-Functions-Activities'!D8) -> Financial Asset Information Management: Financial Asset Information Processing - Heritage Assets and Stewardship Land | B16: EXCL/O | C16: Can be included in service scope for additional cost
A17: =CONCATENATE('FFM-Functions-Activities'!B9,": ",'FFM-Functions-Activities'!D9) -> Financial Asset Information Management: Financial Asset Information Processing - Federal Oil and Gas Resources | B17: EXCL/O | C17: Can be included in service scope for additional cost
A18: =CONCATENATE('FFM-Functions-Activities'!B10,": ",'FFM-Functions-Activities'!D10) -> Financial Asset Information Management: Financial Asset Information Processing - Other Federal Assets | B18: EXCL/O | C18: Can be included in service scope for additional cost
A19: =CONCATENATE('FFM-Functions-Activities'!B11,": ",'FFM-Functions-Activities'!D11) -> Financial Asset Information Management: Financial Asset Information Reporting | B19: INCL | C19: Included in scope of review
A20: =CONCATENATE('FFM-Functions-Activities'!B12,": ",'FFM-Functions-Activities'!D12) -> Payable Management: Payee Setup and Maintenance | B20: INCL | C20: Included in scope of review
A21: =CONCATENATE('FFM-Functions-Activities'!B13,": ",'FFM-Functions-Activities'!D13) -> Payable Management: Obligation Management | B21: INCL | C21: Included in scope of review
A22: =CONCATENATE('FFM-Functions-Activities'!B14,": ",'FFM-Functions-Activities'!D14) -> Payable Management: Payment Processing - Intragovernmental Payments | B22: INCL | C22: Included in scope of review
... A64: =CONCATENATE('FFM-Functions-Activities'!B56,": ",'FFM-Functions-Activities'!D56) -> Financial / Performance Reporting: Internal Control/Compliance Reviews | B64: INCL | C64: Service Customer must provide results of previous 2 years and any ongoing internal control and compliance reviews to be included in scope of review
A66: Asset View
A67: Service Delivery Resources: | B67: Technology | H67: Workforce | J67: Advisory | L67: Additional Explanation
A68: Cost Pools: | B68: Facilities | C68: Telecom-Network | D68: Hardware | E68: Software | F68: Internal Services | G68: Outside Services | H68: Internal Labor | I68: External Labor | J68: Internal Labor | K68: External Labor
A69: Service Delivery Layers and Towers: Sub-Towers
A70: SL0: Service Delivery Management
A71: IT Management: IT Management and Strategic Planning | B71: N/A | C71: N/A | D71: N/A | E71: N/A | F71: N/A | G71: N/A | H71: N/A | I71: N/A | J71: N/A | K71: N/A
A72: IT Management: Enterprise Architecture | B72: N/A | C72: N/A | D72: N/A | E72: N/A | F72: N/A | G72: N/A | H72: N/A | I72: N/A | J72: N/A | K72: N/A
A73: IT Management: IT Finance | B73: N/A | C73: N/A | D73: N/A | E73: N/A | F73: N/A | G73: N/A | H73: N/A | I73: N/A | J73: N/A | K73: N/A
A74: IT Management: IT Vendor Management | B74: N/A | C74: N/A | D74: N/A | E74: N/A | F74: N/A | G74: N/A | H74: N/A | I74: N/A | J74: N/A | K74: N/A
A75: IT Management: IT Human Capital Management | B75: N/A | C75: N/A | D75: N/A | E75: N/A | F75: N/A | G75: N/A | H75: N/A | I75: N/A | J75: N/A | K75: N/A
A76: IT Management: IT Personnel Travel | B76: N/A | C76: N/A | D76: N/A | E76: N/A | F76: N/A | G76: N/A | H76: N/A | I76: N/A | J76: N/A | K76: N/A
A77: Delivery: IT Service Management | B77: N/A | C77: N/A | D77: N/A | E77: N/A | F77: N/A | G77: N/A | H77: N/A | I77: N/A | J77: N/A | K77: N/A
A78: Delivery: Program, Product & Project Management | B78: N/A | C78: N/A | D78: N/A | E78: N/A | F78: N/A | G78: N/A | H78: N/A | I78: N/A | J78: N/A | K78: N/A
A79: Delivery: Client Management | B79: N/A | C79: N/A | D79: N/A | E79: N/A | F79: N/A | G79: N/A | H79: N/A | I79: N/A | J79: N/A | K79: N/A
A80: Delivery: Operations Center | B80: N/A | C80: N/A | D80: N/A | E80: N/A | F80: N/A | G80: N/A | H80: N/A | I80: N/A | J80: N/A | K80: N/A
A81: Delivery: IT Service Design and Improvement | B81: N/A | C81: N/A | D81: N/A | E81: N/A | F81: N/A | G81: N/A | H81: N/A | I81: N/A | J81: N/A | K81: N/A
A82: Security & Compliance: Security | B82: N/A | C82: N/A | D82: N/A | E82: N/A | F82: N/A | G82: N/A | H82: N/A | I82: N/A | J82: N/A | K82: N/A
... A92: Business Management: Business Personnel Travel | B92: N/A | C92: N/A | D92: N/A | E92: N/A | F92: INCL | G92: N/A | H92: INCL | I92: INCL | J92: N/A | K92: INCL
A93: SL1: Facilities and Telecommunications
A94: Data Center: Enterprise Data Center | B94: N/A | C94: N/A | D94: N/A | E94: N/A | F94: N/A | G94: N/A | H94: N/A | I94: N/A | J94: N/A | K94: N/A
A95: Data Center: Other IT Facilities | B95: N/A | C95: N/A | D95: N/A | E95: N/A | F95: N/A | G95: N/A | H95: N/A | I95: N/A | J95: N/A | K95: N/A
A96: Data Center: IT Transport Vehicles & Equipment | B96: N/A | C96: N/A | D96: N/A | E96: N/A | F96: N/A | G96: N/A | H96: N/A | I96: N/A | J96: N/A | K96: N/A
A97: Data Center: IT Office Furniture & Supplies | B97: N/A | C97: N/A | D97: N/A | E97: N/A | F97: N/A | G97: N/A | H97: N/A | I97: N/A | J97: N/A | K97: N/A
A98: Business Facilities, Equipment & Supplies: Business Facilities | B98: EXCL/R* | C98: N/A | D98: N/A | E98: N/A | F98: N/A | G98: N/A | H98: N/A | I98: N/A | J98: N/A | K98: N/A | L98: Service Customer to provide office space for Service Provider staff.
A99: Business Facilities, Equipment & Supplies: Business Transport Vehicles & Equipment | B99: N/A | C99: N/A | D99: N/A | E99: N/A | F99: N/A | G99: N/A | H99: N/A | I99: N/A | J99: N/A | K99: N/A
A100: Business Facilities, Equipment & Supplies: Business Office Furniture & Supplies | B100: EXCL/R* | C100: N/A | D100: N/A | E100: N/A | F100: N/A | G100: N/A | H100: N/A | I100: N/A | J100: N/A | K100: N/A | L100: Service Customer to provide office space for Service Provider staff.
A101: Network: LAN/WAN | B101: N/A | C101: EXCL/R* | D101: N/A | E101: N/A | F101: N/A | G101: EXCL/R* | H101: EXCL/R* | I101: N/A | J101: N/A | K101: N/A | L101: Service Customer to provide network connectivity including internet (outernet) access for Service Provider staff.
A102: Network: Voice | B102: N/A | C102: N/A | D102: N/A | E102: N/A | F102: N/A | G102: N/A | H102: N/A | I102: N/A | J102: N/A | K102: N/A
A103: Network: Transport | B103: N/A | C103: N/A | D103: N/A | E103: N/A | F103: N/A | G103: N/A | H103: N/A | I103: N/A | J103: N/A | K103: N/A
A104: SL2: Hardware/OS/Storage Management
A105: Compute: Servers | B105: N/A | C105: N/A | D105: N/A | E105: N/A | F105: N/A | G105: N/A | H105: N/A | I105: N/A | J105: N/A | K105: N/A
A106: Compute: Unix | B106: N/A | C106: N/A | D106: N/A | E106: N/A | F106: N/A | G106: N/A | H106: N/A | I106: N/A | J106: N/A | K106: N/A
A107: Compute: Midrange | B107: N/A | C107: N/A | D107: N/A | E107: N/A | F107: N/A | G107: N/A | H107: N/A | I107: N/A | J107: N/A | K107: N/A
A108: Compute: Converged Infrastructure | B108: N/A | C108: N/A | D108: N/A | E108: N/A | F108: N/A | G108: N/A | H108: N/A | I108: N/A | J108: N/A | K108: N/A
A109: Compute: Mainframe | B109: N/A | C109: N/A | D109: N/A | E109: N/A | F109: N/A | G109: N/A | H109: N/A | I109: N/A | J109: N/A | K109: N/A
A110: Compute: High Performance Computing | B110: N/A | C110: N/A | D110: N/A | E110: N/A | F110: N/A | G110: N/A | H110: N/A | I110: N/A | J110: N/A | K110: N/A
A111: Storage: Online Storage | B111: N/A | C111: N/A | D111: N/A | E111: N/A | F111: N/A | G111: N/A | H111: N/A | I111: N/A | J111: N/A | K111: N/A
A112: Storage: Mainframe Online Storage | B112: N/A | C112: N/A | D112: N/A | E112: N/A | F112: N/A | G112: N/A | H112: N/A | I112: N/A | J112: N/A | K112: N/A
A113: Storage: Offline Storage | B113: N/A | C113: N/A | D113: N/A | E113: N/A | F113: N/A | G113: N/A | H113: N/A | I113: N/A | J113: N/A | K113: N/A
A114: Storage: Mainframe Offline Storage | B114: N/A | C114: N/A | D114: N/A | E114: N/A | F114: N/A | G114: N/A | H114: N/A | I114: N/A | J114: N/A | K114: N/A
A115: Output: Central Print | B115: N/A | C115: N/A | D115: N/A | E115: N/A | F115: N/A | G115: N/A | H115: N/A | I115: N/A | J115: N/A | K115: N/A
A116: End User: Workspace | B116: N/A | C116: N/A | D116: EXCL/R* | E116: EXCL/R* | F116: N/A | G116: N/A | H116: N/A | I116: N/A | J116: N/A | K116: N/A | L116: Service Customer to provide Service Provider staff end-user computing devices (e.g., laptops) with configured collaboration and productivity software (e.g., Microsoft O365, MSTeams) and end user software required for accessing Core FS solution, (e.g., browser and security application).
A117: End User: Mobile Devices | B117: N/A | C117: N/A | D117: N/A | E117: N/A | F117: N/A | G117: N/A | H117: N/A | I117: N/A | J117: N/A | K117: N/A
A118: End User: Network Printers | B118: N/A | C118: N/A | D118: EXCL/R* | E118: EXCL/R* | F118: N/A | G118: N/A | H118: N/A | I118: N/A | J118: N/A | K118: N/A | L118: Service Customer to provide Service Provider staff with connectivity to and use of printers.
A119: End User: Conferencing & AV | B119: N/A | C119: N/A | D119: N/A | E119: N/A | F119: N/A | G119: N/A | H119: N/A | I119: N/A | J119: N/A | K119: N/A
A120: SL3: Software Management
A121: Platform: Middleware | B121: N/A | C121: N/A | D121: N/A | E121: N/A | F121: N/A | G121: N/A | H121: N/A | I121: N/A | J121: N/A | K121: N/A
A122: Platform: Mainframe Middleware | B122: N/A | C122: N/A | D122: N/A | E122: N/A | F122: N/A | G122: N/A | H122: N/A | I122: N/A | J122: N/A | K122: N/A
A123: Platform: Container Orchestration | B123: N/A | C123: N/A | D123: N/A | E123: N/A | F123: N/A | G123: N/A | H123: N/A | I123: N/A | J123: N/A | K123: N/A
A124: Application: Application Development | B124: N/A | C124: N/A | D124: N/A | E124: N/A | F124: N/A | G124: N/A | H124: N/A | I124: N/A | J124: N/A | K124: N/A
A125: Application: Application Support | B125: N/A | C125: N/A | D125: N/A | E125: N/A | F125: N/A | G125: N/A | H125: N/A | I125: N/A | J125: N/A | K125: N/A
A126: Application: Business Software | B126: N/A | C126: N/A | D126: N/A | E126: N/A | F126: N/A | G126: N/A | H126: N/A | I126: N/A | J126: N/A | K126: N/A
A127: End User: End User Software | B127: N/A | C127: N/A | D127: N/A | E127: EXCL/R* | F127: N/A | G127: N/A | H127: N/A | I127: N/A | J127: N/A | K127: N/A | L127: Service Customer to provide Service Provider staff end-user computing devices (e.g., laptops) with configured collaboration and productivity software (e.g., Microsoft O365, MSTeams) and end user software required for accessing Core FS solution, (e.g., browser and configuration).
A128: SL4: Data/Content Management
A129: Platform: Database | B129: N/A | C129: N/A | D129: N/A | E129: N/A | F129: N/A | G129: EXCL/R* | H129: N/A | I129: N/A | J129: N/A | K129: N/A | L129: Service Customer to provide Core FS solution database controls documentation.
A130: Platform: Mainframe Database | B130: N/A | C130: N/A | D130: N/A | E130: N/A | F130: N/A | G130: N/A | H130: N/A | I130: N/A | J130: N/A | K130: N/A
A131: Platform: Big Data | B131: N/A | C131: N/A | D131: N/A | E131: N/A | F131: N/A | G131: N/A | H131: N/A | I131: N/A | J131: N/A | K131: N/A
A132: Application: Data Mgmt & Operations | B132: N/A | C132: N/A | D132: N/A | E132: N/A | F132: N/A | G132: EXCL/R* | H132: N/A | I132: N/A | J132: N/A | K132: N/A | L132: Service Customer must provide Core FS solution data management and operations documentation.
A133: Application: Data Sourcing & Maintenance | B133: N/A | C133: N/A | D133: N/A | E133: N/A | F133: N/A | G133: N/A | H133: N/A | I133: N/A | J133: N/A | K133: N/A
A134: SL5: Business Application Support
A135: Application: Application Operations | B135: N/A | C135: N/A | D135: N/A | E135: N/A | F135: N/A | G135: EXCL/R* | H135: N/A | I135: N/A | J135: N/A | K135: N/A | L135: Service Customer to provide Core FS solution operations documentation
A136: End User: IT Help Desk | B136: N/A | C136: N/A | D136: N/A | E136: N/A | F136: N/A | G136: N/A | H136: N/A | I136: N/A | J136: N/A | K136: N/A
A137: End User: Deskside Support | B137: N/A | C137: N/A | D137: N/A | E137: N/A | F137: N/A | G137: N/A | H137: N/A | I137: N/A | J137: N/A | K137: N/A
A138: End User: Application Training | B138: N/A | C138: N/A | D138: N/A | E138: N/A | F138: N/A | G138: N/A | H138: N/A | I138: N/A | J138: N/A | K138: N/A
A139: SL6: Business Transaction/Information Processing Support
A140: Business Delivery Mgmt & Support: Transaction/Information Processing | B140: N/A | C140: N/A | D140: N/A | E140: N/A | F140: N/A | G140: N/A | H140: N/A | I140: N/A | J140: N/A | K140: N/A
A141: SL7: Business Functional and Analytics Support
A142: Business Delivery Mgmt & Support: Business Function Training | B142: N/A | C142: N/A | D142: N/A | E142: N/A | F142: N/A | G142: N/A | H142: N/A | I142: N/A | J142: N/A | K142: N/A
A143: Business Delivery Mgmt & Support: Reporting and Data Analysis | B143: N/A | C143: N/A | D143: N/A | E143: INCL | F143: N/A | G143: N/A | H143: INCL | I143: INCL | J143: N/A | K143: INCL | L143: Service Provider will provide data analysis templates and macros to be loaded onto Service Customer-provided end-user computing devices
A144: Compliance & Controls: Regulation and Policy Guidance | B144: N/A | C144: N/A | D144: N/A | E144: N/A | F144: N/A | G144: N/A | H144: INCL | I144: INCL | J144: N/A | K144: INCL
A145: Compliance & Controls: Internal Control & Audit | B145: N/A | C145: N/A | D145: N/A | E145: INCL | F145: N/A | G145: N/A | H145: INCL | I145: INCL | J145: N/A | K145: INCL | L145: Service Provider will provide audit templates and macros to be loaded onto Service Customer-provided end-user computing devices

Sheet FFM-Functions-Activities
A1: PRE-DECISIONAL DRAFT (May 26, 2021) Any text in the ServiceActivityDescripton column noted in red indicates a proposed change from the standard previously released in February 2021. An official copy of the finalized version will be released in the summer of 2021.
A2: FunctionAreaID | B2: ServiceFunctionName | C2: ServiceActivityID | D2: ServiceActivityName | E2: ServiceActivityDescription
A3: FFM.010 | B3: Budget Execution | C3: FFM.010.010 | D3: Budget Setup and Maintenance | E3: Establish and maintain budgetary resource reporting attributes; Receive agency spend and operating plan; Establish and maintain appropriated fund subdivisions before any of the appropriated funds are expended, according to OMB apportionments and agency spend and operating plan; Set up the funds control structure, levels, and accounting segments; Record the Treasury Accounting Fund Symbol (TAFS)/ Program/ Project/ Activity (PPA) information and organizational information for allotment and allocation; Includes setting up direct, reimbursable, revolving, contract, borrowing, financing, liquidating, advanced appropriation, anticipated collections, and non-expenditure transfer funds; Includes recording appropriation warrants, apportionments, allotments, allowances, allocations, reapportionments, transfer allocations, continuing resolutions, rescissions, and reprogramming actions
A4: FFM.010 | B4: Budget Execution | C4: FFM.010.020 | D4: Fund Allocation and Control | E4: Implement controls designed to detect or prevent overspending for defined accounting segments; Execute statutory limitation control of funds restricting obligations and expenditures to amounts authorized by law; Execute administrative control of funds restricting obligation and expenditure from each account to the lower of the amount apportioned by OMB or the amount available for obligation and/or expenditure; Update funds control rules
A5: FFM.010 | B5: Budget Execution | C5: FFM.010.030 | D5: Budgetary Reporting | E5: Perform budgetary resource and budget execution analysis; Provide cumulative budgetary resource and budget execution reports to governing financial management authorities (e.g. OMB); Provide reports of impacts from unusual events, such as sequestration, rescission, and deferrals; Provide reports on Antideficiency Act violations; Includes generating SF-132 and SF-133 and providing information needed for Budget Formulation; Verify required budgetary reports (e.g., SF-133) and general ledger account balances can be traced to appropriate supporting documentation
A6: FFM.020 | B6: Financial Asset Information Management | C6: FFM.020.010 | D6: Financial Asset Information Processing - Property, Plant, and Equipment | E6: Record financial asset type, category, value, and value adjustments (e.g., depreciation, impairment); Includes financial asset information processing for purchase and lease transactions, inventory, constructed assets and software
A7: FFM.020 | B7: Financial Asset Information Management | C7: FFM.020.020 | D7: Financial Asset Information Processing - Loans | E7: Record financial asset type, category, value, and value adjustments (e.g., allowance for uncollectible amounts, subsidy allowance)
A8: FFM.020 | B8: Financial Asset Information Management | C8: FFM.020.030 | D8: Financial Asset Information Processing - Heritage Assets and Stewardship Land | E8: Record financial asset type, category, value, and value adjustments (e.g., depreciation, impairment)
A9: FFM.020 | B9: Financial Asset Information Management | C9: FFM.020.040 | D9: Financial Asset Information Processing - Federal Oil and Gas Resources | E9: Record financial asset type, category, value, and value adjustments
A10: FFM.020 | B10: Financial Asset Information Management | C10: FFM.020.050 | D10: Financial Asset Information Processing - Other Federal Assets | E10: Record financial asset type, category, value, and value adjustments; Includes financial asset information processing for seized and forfeited assets and investments in Treasury securities
A11: FFM.020 | B11: Financial Asset Information Management | C11: FFM.020.060 | D11: Financial Asset Information Reporting | E11: Provide financial asset information (e.g., asset type, value) for financial reporting and reconciliation with information in the asset management systems
A12: FFM.030 | B12: Payable Management | C12: FFM.030.010 | D12: Payee Setup and Maintenance | E12: Establish and maintain federal and nonfederal payee information; Validate payee information against other payee information sources (e.g. SAM, Do Not Pay List)
A13: FFM.030 | B13: Payable Management | C13: FFM.030.020 | D13: Obligation Management | E13: Record commitments (if applicable); Record obligations for both procurement and non-procurement purchases; Includes decommitments/ modifications, liquidating commitments, deobligations/ modifications, and liquidating obligations; Includes capturing obligation information as required to support the Digital Accountability and Transparency Act of 2014 (DATA Act); Includes verifying the validity of the undelivered orders balance
... A56: FFM.110 | B56: Financial / Performance Reporting | C56: FFM.110.050 | D56: Internal Control/Compliance Reviews | E56: Implement standard internal control and compliance assurance procedures; Provide documentation to satisfy “Prepared By Client” requests from auditors; Prepare cycle memos; Provide sample information and documentation for compliance with other guidance, such as OMB Circular A-123; Record adjustments based on audit findings

Sheet Serv Delivery Layers
G1: Draft/Pre-Decisional
G2: This RFI (Request for Information) is issued solely for market research and planning purposes. The RFI does not constitute a solicitation or a commitment to a particular acquisition strategy. The RFI is intended to get industry feedback on the vision for the FM QSMO Marketplace, which includes core financial system and other financial management services and solutions. Nothing in this document should be construed as a final government decision upon which industry should take action and the RFI is subject to change. Treasury is not seeking proposals at this time and will not consider unsolicited proposals provided in response to the RFI. All information received in response to the RFI that is marked as proprietary will be handled accordingly. Responses to this notice are not offers and cannot be accepted by the Government to form a binding contract. Responders are solely responsible for all expenses associated with responding to the RFI.
B7: Service Delivery Layers and Resources
B8: As of: May 26, 2021
B40: It is anticipated that offerings in each of the FM QSMO Marketplace categories may include one or more of the following types of Service Delivery Resources: • Technology – the physical assets needed to deliver to FM solution/service • Workforce – the personnel that plan, build, implement, operate and/or deliver the FM solution/service on an on-going basis • Advisory – the personnel that advise, guide, consult and/or perform Independent Verification and Validation on an as-needed basis. It is also anticipated that offerings in each of the FM QSMO Marketplace categories may include one or more of the following types of Service Delivery Layers: • Service Delivery Layer 0 – components supporting the overall management of the FM solution/service and cross-Service Layer functions such as asset and configuration management, security and privacy assurance and audit, and Disaster Recovery (DR) and Continuity of Operations (COOP) management • Service Layers 1 and 2 – components such as hardware, operating system software, and storage, as well as the facilities they are housed in and the networks needed to connect these technologies (all together commonly referred to as the “infrastructure”) • Service Layers 3, 4, and 5 – components providing enterprise, middleware, or business application software, managing content and data, and providing technical support for the business applications • Service Layers 6 and 7 – components supporting business operations such as transaction processing, document or data pre-processing, business function guidance, data reporting, and data analyses.

Sheet Towers-SubTowers
C1: Draft/Pre-Decisional
C2: This RFI (Request for Information) is issued solely for market research and planning purposes. The RFI does not constitute a solicitation or a commitment to a particular acquisition strategy. The RFI is intended to get industry feedback on the vision for the FM QSMO Marketplace, which includes core financial system and other financial management services and solutions. Nothing in this document should be construed as a final government decision upon which industry should take action and the RFI is subject to change. Treasury is not seeking proposals at this time and will not consider unsolicited proposals provided in response to the RFI. All information received in response to the RFI that is marked as proprietary will be handled accordingly. Responses to this notice are not offers and cannot be accepted by the Government to form a binding contract. Responders are solely responsible for all expenses associated with responding to the RFI.
A6: Towers-SubTowers
A7: =Overview!A4 -> As of: May 26, 2021 | C7: The high-level list and description of the commercial TBM Taxonomy Towers/Sub-Towers (https://higherlogicdownload.s3.amazonaws.com/TBMCOUNCIL/c15d372f-9951-46c8-9c3f-213c696401b6/UploadedImages/TBM_Taxonomy_V4_0.pdf) has been augmented with government-defined extensions to fully account for other anticipated service delivery components and costs not explicitly addressed in the commercial TBM Tower/Sub-Tower descriptions.
A8: Light Blue = Commercial TBM v4 | C8: Gold = Federal Government Extension
A9: Tower ID | B9: Tower Name | C9: Sub-Tower ID | D9: Tower/Sub-Tower Name | E9: Tower/Sub-Tower Description
A10: 0.1 | B10: IT Management | E10: The IT Management tower includes the costs to manage, administer & plan IT for the enterprise. It includes executive management, strategic management, enterprise architecture, IT finance, and vendor management.
A11: 0.1 | B11: IT Management | C11: 0.1.1 | D11: IT Management & Strategic Planning | E11: IT management and administration resources; typically CIO, senior IT leaders and administrative support including centralized IT strategy and planning.
A12: 0.1 | B12: IT Management | C12: 0.1.2 | D12: Enterprise Architecture | E12: Enterprise architecture services including business, information, application and technical architecture to drive standardization, integration and efficiency among business technology solutions.
A13: 0.1 | B13: IT Management | C13: 0.1.3 | D13: IT Finance | E13: Resources involved in the planning, budgeting, spend management and chargeback of IT expenditures and the costing of IT products and services.
A14: 0.1 | B14: IT Management | C14: 0.1.4 | D14: IT Vendor Management | E14: Resources involved in the selection, contract management, oversight, performance management and general delivery of IT services by 3rd party vendors and external service providers.
A15: 0.1 | B15: IT Management | C15: 0.1.5 | D15: IT Human Capital Management | E15: Resources involved in the acquisition, development, performance management, compensation, and separation of IT personnel. Included are initial and periodic personnel background investigations and drug testing, as well as training on organizational policies and procedures.
A16: 0.1 | B16: IT Management | C16: 0.1.6 | D16: IT Personnel Travel | E16: Any IT personnel travel related to official work.
A17: 0.2 | B17: Delivery | E17: The delivery tower includes the costs to monitor, support, manage, and run IT operations for the enterprise and includes the IT Service Management (ITSM) functions.
A18: 0.2 | B18: Delivery | C18: 0.2.1 | D18: IT Service Management | E18: Resources involved with the incident, problem and change management activities as part of the IT Service Management process (excludes the Tier 1 help desk).
A19: 0.2 | B19: Delivery | C19: 0.2.2 | D19: IT Program, Product & Project Management | E19: Resources involved with managing and supporting IT related projects and/or continuous product development (e.g. Agile) across business and IT-driven initiatives.
A20: 0.2 | B20: Delivery | C20: 0.2.3 | D20: Client Management | E20: Resources or “account managers” aligned with the lines of business to understand business needs, communicate IT products, services and status of IT projects.
A21: 0.2 | B21: Delivery | C21: 0.2.4 | D21: Operations Center | E21: Centralized IT Operations Center resources including monitoring and intervention e.g., NOC (network operations center), GOC (global operations center).
A22: 0.2 | B22: Delivery | C22: 0.2.5 | D22: IT Service Design and Improvement | E22: Resources involved with designing, monitoring, reporting, and improving services, including the associated service catalogue, service measures, and service agreements.
A23: 0.3 | B23: Security & Compliance | E23: The Security & Compliance tower includes service costs related to IT security compliance and disaster recovery. The scope includes costs to define, establish, enforce, and measure security, compliance, and disaster recovery readiness for the enterprise.
A24: 0.3 | B24: Security & Compliance | C24: 0.3.1 | D24: Security | E24: IT Security resources setting policy, establishing process & means, measuring compliance and responding to security breaches and providing real-time operational security such as vulnerability scanning, managing firewalls, intrusion prevention systems, and security information and event management (SIEM). Optional Level 3 categories include: Cyber Security. The implementation actions defined by security policies (e.g. mitigating security breaches by applying patches) are not included in the Security sub-tower and are part of the respective towers where the actions take place (e.g. Compute, Storage, Network).
A25: 0.3 | B25: Security & Compliance | C25: 0.3.2 | D25: Compliance | E25: IT Compliance resources setting policy, establishing controls and measuring compliance to relevant legal and compliance requirements. Optional Level 3 categories include: Data Privacy. The implementation actions defined by Compliance policy (e.g. implementing controls like multi-factor authentication) are not included in the Compliance subtower and are part of the respective towers where the actions take place (e.g. Compute, Storage, Network, Application, End User).
A26: 0.3 | B26: Security & Compliance | C26: 0.3.3 | D26: Disaster Recovery | E26: IT Disaster Recovery resources setting DR policy, establishing process & means, dedicated failover facilities, performing DR testing. NOTE: DR designated equipment is included directly in its own sub-tower (e.g., extra servers for DR are included in Compute tower, etc.). The implementation actions defined by Disaster Recovery policy (e.g. building DR servers) are not included in the Disaster & Recovery sub-tower and are part of the respective towers where the actions take place (e.g. Compute, Storage, Network).
A27: 0.3 | B27: Security & Compliance | C27: 0.3.4 | D27: Federal Records Mgmt | E27: Resources establishing process, means and controls for ensuring compliance with the Federal Government's policies and procedures for creating, maintaining, and disposing of Federal electronic and digitized paper records.
A28: 1.1 | B28: Data Center | E28: Data Centers are purpose-built facilities to securely house computer equipment. Data Centers provide racks/cabinets & cabling, clean & redundant power, data connectivity, environmental controls including temperature, humidity and fire suppression, physical security and the people to run and operate the facility and its infrastructure.
A29: 1.1 | B29: Data Center | C29: 1.1.1 | D29: Enterprise Data Center | E29: Purpose-built data center facilities that house and protect critical IT equipment including the space, power, environment controls, racks, cabling and "smart hand" support.
A30: 1.1 | B30: Data Center | C30: 1.1.2 | D30: Other IT Facilities | E30: Computer rooms and MDF/IDF/telco closets that house IT equipment in corporate headquarters, call centers or other general purpose office buildings.
A31: 1.1 | B31: Data Center | C31: 1.1.3 | D31: IT Transport Vehicles & Equipment | E31: Vehicles and equipment for transport of IT personnel and assets.
A32: 1.1 | B32: Data Center | C32: 1.1.4 | D32: IT Office Furniture & Supplies | E32: Furniture and supplies for IT offices.
A33: 1.2 | B33: Network | E33: Network includes the data and voice equipment along with the transport methods to connect systems and people and to enable people to converse. Networks provide core connectivity within the enterprise data centers as well as connectivity to and access within office building and remote locations.
A34: 1.2 | B34: Network | C34: 1.2.1 | D34: LAN/WAN | E34: Physical and wireless local area network connecting equipment within the core data centers and connecting end users in office working areas to the organization's broader networks. Wide area network equipment, labor and support services directly connecting data centers, offices and third parties (excludes telecom and communication services). Optional Level 3 categories include: LAN, WAN.
A35: 1.2 | B35: Network | C35: 1.2.2 | D35: Voice | E35: Voice resources which enable or distribute voice services through on premise equipment including PBX, VoIP, voicemail and handsets (excludes telecom and communication services).
A36: 1.2 | B36: Network | C36: 1.2.3 | D36: Transport | E36: Data network circuits and associated access facilities and services; includes dedicated and virtual data networks and internet access. Also includes usage associated with mobility and other data transit based on usage billing. Voice network circuits and associated access facilities and services. Also includes usage associated with standard telephone calls and 800 number service. Both voice and data transport may include terrestrial and non-terrestrial (e.g., satellite) technologies. Optional Level 3 categories include: Data, Voice.
A37: 2.1 | B37: Compute | E37: Compute refers to both general and special-purpose devices and software that are programmed to carry out a set of arithmetic or logical operations. In essence, it provides the “brains” to process application and user requests. Compute includes a wide range of physical and virtual servers differentiated by platform and operating system. The Compute tower should include all direct hardware, software, labor and outside service costs.
A38: 2.1 | B38: Compute | C38: 2.1.1 | D38: Servers | E38: Physical and virtual servers running a version of Microsoft's Windows Server or the Linux operating system; includes hardware, software, labor and support services. Optional Level 3 categories include: Windows, Linux and Public Cloud Compute.
A39: 2.1 | B39: Compute | C39: 2.1.2 | D39: Unix | E39: Servers running vendor-specific, proprietary Unix operating systems (e.g., IBM AIX, Sun Solaris, HP UX); includes hardware, software, labor and support services.
A40: 2.1 | B40: Compute | C40: 2.1.3 | D40: Midrange | E40: Servers running IBM AS/400 platform including hardware, software, labor and support services.
A41: 2.1 | B41: Compute | C41: 2.1.4 | D41: Converged Infrastructure | E41: Purpose-built appliances that provide compute, storage and network capabilities in one box.
A42: 2.1 | B42: Compute | C42: 2.1.5 | D42: Mainframe | E42: Traditional mainframe computers and operations running legacy operating systems.
A43: 2.1 | B43: Compute | C43: 2.1.6 | D43: High Performance Computing | E43: Purpose-built servers that use parallel processing and clustering for running advanced application programs and for solving complex computational problems efficiently, reliably and quickly.
A44: 2.2 | B44: Storage | E44: Storage provides centralized data storage and securely holds information and data to be retrieved later. Storage may hold data for application programs and code, databases, files, media, email and many other forms of information. The storage tower includes distributed and mainframe storage that provides on-line storage for real-time access and archival storage solutions that may enable near-term retrieval or long-term archival. The storage tower excludes the internal storage included with a typical server configuration or end-user device such as a laptop, desktop or mobile phone, or tablet.
A45: 2.2 | B45: Storage | C45: 2.2.1 | D45: Online Storage | E45: Central storage such as SAN, NAS and similar technologies for the distributed compute infrastructure; includes the equipment, software and labor to run and operate. Optional Level 3 categories include: On-Premise, Public Cloud Storage.
A46: 2.2 | B46: Storage | C46: 2.2.2 | D46: Offline Storage | E46: Offline storage resources used for archive, backup & recovery to support data loss, data corruption, disaster recovery and compliance requirements of the distributed storage.
A47: 2.2 | B47: Storage | C47: 2.2.3 | D47: Mainframe Online Storage | E47: Mainframe attached storage arrays and the associated equipment, software and labor to run and operate.
A48: 2.2 | B48: Storage | C48: 2.2.4 | D48: Mainframe Offline Storage | E48: Any storage resources used for archive, backup & recovery to support data loss, data corruption, disaster recovery and compliance requirements of the mainframe storage.
A49: 2.3 | B49: Output | E49: Output includes the central print services to provide high-volume printing of customer bills, checks, product documentation or other customer support materials. Output also includes additional post print processing support (e.g. fold, stuff, apply postage, bundle).
A50: 2.3 | B50: Output | C50: 2.3.1 | D50: Central Print | E50: Central print services; often provided to support customer billing or customer documentation support processes. Unit of measure: page.
A51: 2.4 | B51: Platform | E51: Platform includes all costs associated with distributed and mainframe databases and middleware systems. Costs include DBMS software and tools, labor and outside services.
A52: 2.4 | B52: Platform | C52: 2.4.1 | D52: Database | E52: Distributed database services focused on the physical database (versus the logical design) including DBAs, DBMS, tools and operational support.
A53: 2.4 | B53: Platform | C53: 2.4.2 | D53: Middleware | E53: Distributed platform, application and system integration resources enabling cross application development, communications and information sharing.
A54: 2.4 | B54: Platform | C54: 2.4.3 | D54: Mainframe Database | E54: Mainframe database services focused on the physical database (versus the logical design) including the DBAs, DBMS, tools and operational support.
A55: 2.4 | B55: Platform | C55: 2.4.4 | D55: Mainframe Middleware | E55: Mainframe platform, application and system integration resources enabling cross application development, communications and information sharing.
A56: 2.4 | B56: Platform | C56: 2.4.5 | D56: Container Orchestration | E56: Tools and resources for managing the lifecycles of containers. Includes the control and automation of tasks such as provisioning and deployment of containers, maintaining availability, scaling up or removing containers to manage application loads, relocating containers, allocating resources for containers, and monitoring container and host health.
A57: 2.4 | B57: Platform | C57: 2.4.6 | D57: Big Data | E57: Systems and resources for integrating, managing and analyzing high volumes of low density, unstructured data that is received at high rates of velocity.
A58: 3.1 | B58: Application | E58: The Application tower includes costs related to applications in the enterprise. The scope includes the cost of business software and the costs to develop, manage and run applications for the enterprise.
A59: 3.1 | B59: Application | C59: 3.1.1 | D59: Application Development | E59: Resources involved with the analysis, design, development, code, test and release packaging services associated with application development projects. Optional Level 3 categories include: Development, QA
A60: 3.1 | B60: Application | C60: 3.1.2 | D60: Application Support & Operations | E60: The operations, support, fix and minor enhancements associated with existing applications.
A61: 3.1 | B61: Application | C61: 3.1.3 | D61: Business Software | E61: Software expenditures including licensing, maintenance and support related to off-the-shelf software purchases.
A62: 3.1 | B62: Application | C62: 3.1.4 | D62: Data Mgmt & Operations | E62: The applications and services supporting the data management and data operations of the enterprise, including but not limited to Data Governance, Master Data Management, Metadata Management, Data Quality, Data Synchronization, Data Interoperability, Database and Schema Design, and File Management.
A63: 3.1 | B63: Application | C63: 3.1.5 | D63: Data Sourcing & Maintenance | E63: The subscriptions, processes, and procedures for acquiring, perfecting and maintaining data sources and data services for use. It also includes maintenance of reference, translation, and validation data used by multiple applications.
A64: 4.1 | B64: End User | E64: End User includes end user computing devices and support for end users. The scope includes costs to build, manage and run end user computing devices for the enterprise and deliver centralized support to end users.
A65: 4.1 | B65: End User | C65: 4.1.1 | D65: Workspace | E65: Client compute physical desktops, portable laptops, thin client machines, peripherals (including monitors, pointer devices and attached personal printers) used by individuals to perform work.
A66: 4.1 | B66: End User | C66: 4.1.2 | D66: Mobile Devices | E66: Client compute tablets, smart phones (iOS, Android, Windows Mobile) and apps used by individuals to perform work.
A67: 4.1 | B67: End User | C67: 4.1.3 | D67: End User Software | E67: Client related software used to author, create, collaborate and share documents and other content. Examples include email, communications, messaging, word processing, spreadsheets, presentations, desktop publishing, graphics and others. Optional Level 3 categories include Productivity; Communications; Collaboration.
A68: 4.1 | B68: End User | C68: 4.1.4 | D68: Network Printers | E68: Printers located on or near users’ desktops. Examples include network connected personal printers, ink-jet printers, laser printers, departmental or copy-room printers. Only include network connected printers. Do not include printers connected to an end user computer.
A69: 4.1 | B69: End User | C69: 4.1.5 | D69: Conferencing & AV | E69: Audio and video conferencing equipment typically used in conference rooms and dedicated telepresence rooms to enable workforce communications.
A70: 4.1 | B70: End User | C70: 4.1.6 | D70: IT Help Desk | E70: Centralized Tier 1 help desk resources that handle user requests, answer questions and resolve issues.
A71: 4.1 | B71: End User | C71: 4.1.7 | D71: Deskside Support | E71: Local support resources that provide on-site support for moves, adds, changes and hands on issue resolution.
A72: 4.1 | B72: End User | C72: 4.1.8 | D72: Application Training | E72: The resources involved with the analysis, design, development, and delivery of training on applications and software tools.
A73: 6.1 | B73: Business Facilities, Equipment & Supplies | C73: 6.1.1 | D73: Business Facilities | E73: Facilities that house business division management and operations.
A74: 6.1 | B74: Business Facilities, Equipment & Supplies | C74: 6.1.2 | D74: Business Transport Vehicles & Equipment | E74: Vehicles and equipment for transport of business division personnel and assets.
A75: 6.1 | B75: Business Facilities, Equipment & Supplies | C75: 6.1.3 | D75: Business Office Furniture & Supplies | E75: Furniture and supplies for business division offices.
A76: 6.2 | B76: Business Delivery Mgmt & Support | C76: 6.2.1 | D76: Business Program, Product & Project Mgmt | E76: Resources involved with managing and supporting business division programs, products/services, or projects.
... A87: 6.4 | B87: Business Management | C87: 6.4.5 | D87: Business Personnel Travel | E87: Any business division personnel travel related to official work.

Sheet Service Components List
C1: Draft/Pre-Decisional
C2: This RFI (Request for Information) is issued solely for market research and planning purposes. The RFI does not constitute a solicitation or a commitment to a particular acquisition strategy. The RFI is intended to get industry feedback on the vision for the FM QSMO Marketplace, which includes core financial system and other financial management services and solutions. Nothing in this document should be construed as a final government decision upon which industry should take action and the RFI is subject to change. Treasury is not seeking proposals at this time and will not consider unsolicited proposals provided in response to the RFI. All information received in response to the RFI that is marked as proprietary will be handled accordingly. Responses to this notice are not offers and cannot be accepted by the Government to form a binding contract. Responders are solely responsible for all expenses associated with responding to the RFI.
A3: Service Components List
A4: ='Cover Page'!A16 -> As of: May 26, 2021
A6: Service Component ID | B6: Service Component Name | C6: Service Component Notes | D6: Service Layer | E6: Service Type | F6: Tower ID | G6: Tower Name | H6: Sub-Tower ID | I6: Sub-Tower Name | J6: Cost Pool ID | K6: Cost Pool Name | L6: Sub-Cost Pool ID | M6: Sub-Cost Pool Name | N6: ITIL Practice Area: Practice
A7: 0.01.01 | B7: Executive Management Personnel - Government | C7: Includes pay and other benefits | D7: SL0: Service Delivery Management | E7: Workforce | F7: 0.1 | G7: IT Management | H7: 0.1.1 | I7: IT Management & Strategic Planning | J7: 2.1 | K7: Internal Labor | L7: 2.1.1 | M7: Expense | N7: General Management: Project Management; General Management: Relationship Management
A8: 0.01.02 | B8: Executive Management Personnel - Contractor | D8: SL0: Service Delivery Management | E8: Workforce | F8: 0.1 | G8: IT Management | H8: 0.1.1 | I8: IT Management & Strategic Planning | J8: 3.1 | K8: External Labor | L8: 3.1.1 | M8: Expense | N8: General Management: Project Management; General Management: Relationship Management
A9: 0.02.01 | B9: Program Management Personnel - Government | C9: Includes pay and other benefits | D9: SL0: Service Delivery Management | E9: Workforce | F9: 0.2 | G9: Delivery | H9: 0.2.2 | I9: IT Program, Product & Project Management | J9: 2.1 | K9: Internal Labor | L9: 2.1.1 | M9: Expense | N9: General Management: Project Management; General Management: Relationship Management; General Management: Risk Management; General Management: Knowledge Management
A10: 0.02.02 | B10: Program Management Personnel - Contractor | D10: SL0: Service Delivery Management | E10: Workforce | F10: 0.2 | G10: Delivery | H10: 0.2.2 | I10: IT Program, Product & Project Management | J10: 3.1 | K10: External Labor | L10: 3.1.1 | M10: Expense | N10: General Management: Project Management; General Management: Relationship Management; General Management: Risk Management; General Management: Knowledge Management
A11: 0.02.03.01 | B11: Program Management Tools Support Personnel - Government | C11: Includes pay and other benefits | D11: SL0: Service Delivery Management | E11: Workforce | F11: 0.2 | G11: Delivery | H11: 0.2.2 | I11: IT Program, Product & Project Management | J11: 2.1 | K11: Internal Labor | L11: 2.1.1 | M11: Expense | N11: General Management: Project Management; General Management: Relationship Management; General Management: Risk Management; General Management: Knowledge Management
A12: 0.02.03.02 | B12: Program Management Tools Support Personnel - Contractor | D12: SL0: Service Delivery Management | E12: Workforce | F12: 0.2 | G12: Delivery | H12: 0.2.2 | I12: IT Program, Product & Project Management | J12: 3.1 | K12: External Labor | L12: 3.1.1 | M12: Expense | N12: General Management: Project Management; General Management: Relationship Management; General Management: Risk Management; General Management: Knowledge Management
A13: 0.02.03.03 | B13: Program Management Tools Software License | D13: SL0: Service Delivery Management | E13: Technology | F13: 0.2 | G13: Delivery | H13: 0.2.2 | I13: IT Program, Product & Project Management | J13: 6.1 | K13: Software | L13: 6.1.2 | M13: Licensing | N13: General Management: Project Management; General Management: Relationship Management; General Management: Risk Management; General Management: Knowledge Management
A14: 0.02.03.04 | B14: Program Management Tools Software Vendor Support | D14: SL0: Service Delivery Management | E14: Technology | F14: 0.2 | G14: Delivery | H14: 0.2.2 | I14: IT Program, Product & Project Management | J14: 6.1 | K14: Software | L14: 6.1.3 | M14: Expense | N14: General Management: Project Management; General Management: Relationship Management; General Management: Risk Management; General Management: Knowledge Management
A15: 0.02.04 | B15: Project Management Personnel - Government | C15: Includes pay and other benefits | D15: SL0: Service Delivery Management | E15: Workforce | F15: 0.2 | G15: Delivery | H15: 0.2.2 | I15: IT Program, Product & Project Management | J15: 2.1 | K15: Internal Labor | L15: 2.1.1 | M15: Expense | N15: General Management: Project Management; General Management: Relationship Management; General Management: Risk Management
A16: 0.02.05 | B16: Project Management Personnel - Contractor | D16: SL0: Service Delivery Management | E16: Workforce | F16: 0.2 | G16: Delivery | H16: 0.2.2 | I16: IT Program, Product & Project Management | J16: 3.1 | K16: External Labor | L16: 3.1.1 | M16: Expense | N16: General Management: Project Management; General Management: Relationship Management; General Management: Risk Management
A17: 0.02.06.01 | B17: Project Management Tools Support Personnel - Government | C17: Includes pay and other benefits | D17: SL0: Service Delivery Management | E17: Workforce | F17: 0.2 | G17: Delivery | H17: 0.2.2 | I17: IT Program, Product & Project Management | J17: 2.1 | K17: Internal Labor | L17: 2.1.1 | M17: Expense | N17: General Management: Project Management; General Management: Relationship Management; General Management: Risk Management
A18: 0.02.06.02 | B18: Project Management Tools Support Personnel - Contractor | D18: SL0: Service Delivery Management | E18: Workforce | F18: 0.2 | G18: Delivery | H18: 0.2.2 | I18: IT Program, Product & Project Management | J18: 3.1 | K18: External Labor | L18: 3.1.1 | M18: Expense | N18: General Management: Project Management; General Management: Relationship Management; General Management: Risk Management
A19: 0.02.06.03 | B19: Project Management Tools Software License | D19: SL0: Service Delivery Management | E19: Technology | F19: 0.2 | G19: Delivery | H19: 0.2.2 | I19: IT Program, Product & Project Management | J19: 6.1 | K19: Software | L19: 6.1.2 | M19: Licensing | N19: General Management: Project Management; General Management: Relationship Management; General Management: Risk Management
A20: 0.02.06.04 | B20: Project Management Tools Software Vendor Support | D20: SL0: Service Delivery Management | E20: Technology | F20: 0.2 | G20: Delivery | H20: 0.2.2 | I20: IT Program, Product & Project Management | J20: 6.1 | K20: Software | L20: 6.1.3 | M20: Expense | N20: General Management: Project Management; General Management: Relationship Management; General Management: Risk Management
A21: 0.03.01 | B21: Program/Project Management Evaluation Personnel - Government | C21: Includes pay and other benefits | D21: SL0: Service Delivery Management | E21: Advisory | F21: 0.2 | G21: Delivery | H21: 0.2.2 | I21: IT Program, Product & Project Management | J21: 2.1 | K21: Internal Labor | L21: 2.1.1 | M21: Expense | N21: General Management: Project Management
A22: 0.03.02 | B22: Program/Project Management Evaluation Personnel - Contractor | D22: SL0: Service Delivery Management | E22: Advisory | F22: 0.2 | G22: Delivery | H22: 0.2.2 | I22: IT Program, Product & Project Management | J22: 3.1 | K22: External Labor | L22: 3.1.1 | M22: Expense | N22: General Management: Project Management
A23: 0.04.01 | B23: Enterprise Architecture Engineering Personnel - Government | C23: Includes pay and other benefits | D23: SL0: Service Delivery Management | E23: Workforce | F23: 0.1 | G23: IT Management | H23: 0.1.2 | I23: Enterprise Architecture | J23: 2.1 | K23: Internal Labor | L23: 2.1.1 | M23: Expense | N23: General Management: Architecture Management
A24: 0.04.02 | B24: Enterprise Architecture Engineering Personnel - Contractor | D24: SL0: Service Delivery Management | E24: Workforce | F24: 0.1 | G24: IT Management | H24: 0.1.2 | I24: Enterprise Architecture | J24: 3.1 | K24: External Labor | L24: 3.1.1 | M24: Expense | N24: General Management: Architecture Management
A25: 0.04.03.01 | B25: Enterprise Architecture Engineering Tools Support Personnel - Government | C25: Includes pay and other benefits | D25: SL0: Service Delivery Management | E25: Workforce | F25: 0.1 | G25: IT Management | H25: 0.1.2 | I25: Enterprise Architecture | J25: 2.1 | K25: Internal Labor | L25: 2.1.1 | M25: Expense | N25: General Management: Architecture Management
A26: 0.04.03.02 | B26: Enterprise Architecture Engineering Tools Support Personnel - Contractor | D26: SL0: Service Delivery Management | E26: Workforce | F26: 0.1 | G26: IT Management | H26: 0.1.2 | I26: Enterprise Architecture | J26: 3.1 | K26: External Labor | L26: 3.1.1 | M26: Expense | N26: General Management: Architecture Management
A27: 0.04.03.03 | B27: Enterprise Architecture Engineering Tools Software License | D27: SL0: Service Delivery Management | E27: Technology | F27: 0.1 | G27: IT Management | H27: 0.1.2 | I27: Enterprise Architecture | J27: 6.1 | K27: Software | L27: 6.1.2 | M27: Licensing | N27: General Management: Architecture Management
A28: 0.04.03.04 | B28: Enterprise Architecture Engineering Tools Software Vendor Support | D28: SL0: Service Delivery Management | E28: Technology | F28: 0.1 | G28: IT Management | H28: 0.1.2 | I28: Enterprise Architecture | J28: 6.1 | K28: Software | L28: 6.1.3 | M28: Expense | N28: General Management: Architecture Management
A29: 0.05.01 | B29: Service Strategy Management Personnel - Government | C29: Includes pay and other benefits | D29: SL0: Service Delivery Management | E29: Workforce | F29: 0.2 | G29: Delivery | H29: 0.2.5 | I29: IT Service Design and Improvement | J29: 2.1 | K29: Internal Labor | L29: 2.1.1 | M29: Expense | N29: General Management: Strategy Management; General Management: Portfolio Management
A30: 0.05.02 | B30: Service Strategy Management Personnel - Contractor | D30: SL0: Service Delivery Management | E30: Workforce | F30: 0.2 | G30: Delivery | H30: 0.2.5 | I30: IT Service Design and Improvement | J30: 3.1 | K30: External Labor | L30: 3.1.1 | M30: Expense | N30: General Management: Strategy Management; General Management: Portfolio Management
A31: 0.05.03.01 | B31: Service Strategy Management Tools Support Personnel - Government | C31: Includes pay and other benefits | D31: SL0: Service Delivery Management | E31: Workforce | F31: 0.2 | G31: Delivery | H31: 0.2.5 | I31: IT Service Design and Improvement | J31: 2.1 | K31: Internal Labor | L31: 2.1.1 | M31: Expense | N31: General Management: Strategy Management; General Management: Portfolio Management
A32: 0.05.03.02 | B32: Service Strategy Management Tools Support Personnel - Contractor | D32: SL0: Service Delivery Management | E32: Workforce | F32: 0.2 | G32: Delivery | H32: 0.2.5 | I32: IT Service Design and Improvement | J32: 3.1 | K32: External Labor | L32: 3.1.1 | M32: Expense | N32: General Management: Strategy Management; General Management: Portfolio Management
A33: 0.05.03.03 | B33: Service Strategy Management Tools Software Licenses | D33: SL0: Service Delivery Management | E33: Technology | F33: 0.2 | G33: Delivery | H33: 0.2.5 | I33: IT Service Design and Improvement | J33: 6.1 | K33: Software | L33: 6.1.2 | M33: Licensing | N33: General Management: Strategy Management; General Management: Portfolio Management
A34: 0.05.03.04 | B34: Service Strategy Management Tools Software Vendor Support | D34: SL0: Service Delivery Management | E34: Technology | F34: 0.2 | G34: Delivery | H34: 0.2.5 | I34: IT Service Design and Improvement | J34: 6.1 | K34: Software | L34: 6.1.3 | M34: Expense | N34: General Management: Strategy Management; General Management: Portfolio Management
A35: 0.06.01 | B35: Service Design Management Personnel - Government | C35: Provide coordination and integration between SL0-7 for these processes Includes pay and other benefits | D35: SL0: Service Delivery Management | E35: Workforce | F35: 0.2 | G35: Delivery | H35: 0.2.5 | I35: IT Service Design and Improvement | J35: 2.1 | K35: Internal Labor | L35: 2.1.1 | M35: Expense | N35: Service Management: Business Analysis; Service Management: Change Control; Service Management: Release Management; Service Management: Service Catalogue Management; Service Management: Service Design; Service Management: Service Level Management
A36: 0.06.02 | B36: Service Design Management Personnel - Contractor | C36: Provide coordination and integration between SL0-7 for these processes | D36: SL0: Service Delivery Management | E36: Workforce | F36: 0.2 | G36: Delivery | H36: 0.2.5 | I36: IT Service Design and Improvement | J36: 3.1 | K36: External Labor | L36: 3.1.1 | M36: Expense | N36: Service Management: Business Analysis; Service Management: Change Control; Service Management: Release Management; Service Management: Service Catalogue Management; Service Management: Service Design; Service Management: Service Level Management
A37: 0.06.03.01 | B37: Service Design Management Tools Support Personnel - Government | C37: Provide coordination and integration between SL0-7 for these processes Includes pay and other benefits | D37: SL0: Service Delivery Management | E37: Workforce | F37: 0.2 | G37: Delivery | H37: 0.2.5 | I37: IT Service Design and Improvement | J37: 2.1 | K37: Internal Labor | L37: 2.1.1 | M37: Expense | N37: Service Management: Business Analysis; Service Management: Change Control; Service Management: Release Management; Service Management: Service Catalogue Management; Service Management: Service Design; Service Management: Service Level Management
A38: 0.06.03.02 | B38: Service Design Management Tools Support Personnel - Contractor | C38: Provide coordination and integration between SL0-7 for these processes | D38: SL0: Service Delivery Management | E38: Workforce | F38: 0.2 | G38: Delivery | H38: 0.2.5 | I38: IT Service Design and Improvement | J38: 3.1 | K38: External Labor | L38: 3.1.1 | M38: Expense | N38: Service Management: Business Analysis; Service Management: Change Control; Service Management: Release Management; Service Management: Service Catalogue Management; Service Management: Service Design; Service Management: Service Level Management
A39: 0.06.03.03 | B39: Service Design Management Tools Software Licenses | C39: Provide coordination and integration between SL0-7 for these processes | D39: SL0: Service Delivery Management | E39: Technology | F39: 0.2 | G39: Delivery | H39: 0.2.5 | I39: IT Service Design and Improvement | J39: 6.1 | K39: Software | L39: 6.1.2 | M39: Licensing | N39: Service Management: Business Analysis; Service Management: Change Control; Service Management: Release Management; Service Management: Service Catalogue Management; Service Management: Service Design; Service Management: Service Level Management
A40: 0.06.03.04 | B40: Service Design Management Tools Software Vendor Support | C40: Provide coordination and integration between SL0-7 for these processes | D40: SL0: Service Delivery Management | E40: Technology | F40: 0.2 | G40: Delivery | H40: 0.2.5 | I40: IT Service Design and Improvement | J40: 6.1 | K40: Software | L40: 6.1.3 | M40: Expense | N40: Service Management: Business Analysis; Service Management: Change Control; Service Management: Release Management; Service Management: Service Catalogue Management; Service Management: Service Design; Service Management: Service Level Management
A41: 0.07.01 | B41: Service Transition Management Personnel - Government | C41: Provide coordination and integration between SL0-7 for these processes Includes pay and other benefits | D41: SL0: Service Delivery Management | E41: Workforce | F41: 0.2 | G41: Delivery | H41: 0.2.5 | I41: IT Service Design and Improvement | J41: 2.1 | K41: Internal Labor | L41: 2.1.1 | M41: Expense | N41: General Management: Organizational Change Management; Technical Management: Deployment Management
A42: 0.07.02 | B42: Service Transition Management Personnel - Contractor | C42: Provide coordination and integration between SL0-7 for these processes | D42: SL0: Service Delivery Management | E42: Workforce | F42: 0.2 | G42: Delivery | H42: 0.2.5 | I42: IT Service Design and Improvement | J42: 3.1 | K42: External Labor | L42: 3.1.1 | M42: Expense | N42: General Management: Organizational Change Management; Technical Management: Deployment Management
A43: 0.07.03.01 | B43: Service Transition Management Tools Support Personnel - Government | C43: Provide coordination and integration between SL0-7 for these processes Includes pay and other benefits | D43: SL0: Service Delivery Management | E43: Workforce | F43: 0.2 | G43: Delivery | H43: 0.2.5 | I43: IT Service Design and Improvement | J43: 2.1 | K43: Internal Labor | L43: 2.1.1 | M43: Expense | N43: General Management: Organizational Change Management; Technical Management: Deployment Management
A44: 0.07.03.02 | B44: Service Transition Management Tools Support Personnel - Contractor | C44: Provide coordination and integration between SL0-7 for these processes | D44: SL0: Service Delivery Management | E44: Workforce | F44: 0.2 | G44: Delivery | H44: 0.2.5 | I44: IT Service Design and Improvement | J44: 3.1 | K44: External Labor | L44: 3.1.1 | M44: Expense | N44: General Management: Organizational Change Management; Technical Management: Deployment Management
A45: 0.07.03.03 | B45: Service Transition Management Tools Software Licenses | C45: Provide coordination and integration between SL0-7 for these processes | D45: SL0: Service Delivery Management | E45: Technology | F45: 0.2 | G45: Delivery | H45: 0.2.5 | I45: IT Service Design and Improvement | J45: 6.1 | K45: Software | L45: 6.1.2 | M45: Licensing | N45: General Management: Organizational Change Management; Technical Management: Deployment Management
A46: 0.07.03.04 | B46: Service Transition Management Tools Software Vendor Support | C46: Provide coordination and integration between SL0-7 for these processes | D46: SL0: Service Delivery Management | E46: Technology | F46: 0.2 | G46: Delivery | H46: 0.2.5 | I46: IT Service Design and Improvement | J46: 6.1 | K46: Software | L46: 6.1.3 | M46: Expense | N46: General Management: Organizational Change Management; Technical Management: Deployment Management
... A63: 0.11.01 | B63: Finance and Accounting Support Personnel - Government | C63: Includes pay and other benefits | D63: SL0: Service Delivery Management | E63: Workforce | F63: 0.1 | G63: IT Management | H63: 0.1.3 | I63: IT Finance | J63: 2.1 | K63: Internal Labor | L63: 2.1.1 | M63: Expense | N63: General Management: Service Financial Management
A64: 0.11.02 | B64: Finance and Accounting Support Personnel - Contractor | D64: SL0: Service Delivery Management | E64: Workforce | F64: 0.1 | G64: IT Management | H64: 0.1.3 | I64: IT Finance | J64: 3.1 | K64: External Labor | L64: 3.1.1 | M64: Expense | N64: General Management: Service Financial Management
A65: 0.11.03 | B65: Finance and Accounting Support Systems License | D65: SL0: Service Delivery Management | E65: Technology | F65: 0.1 | G65: IT Management | H65: 0.1.3 | I65: IT Finance | J65: 6.1 | K65: Software | L65: 6.1.2 | M65: Licensing | N65: General Management: Service Financial Management
A66: 0.11.04 | B66: Finance and Accounting Support Systems Vendor Support | D66: SL0: Service Delivery Management | E66: Technology | F66: 0.1 | G66: IT Management | H66: 0.1.3 | I66: IT Finance | J66: 6.1 | K66: Software | L66: 6.1.3 | M66: Expense | N66: General Management: Service Financial Management
A67: 0.12.01 | B67: HR Support Personnel - Government | C67: Includes pay and other benefits | D67: SL0: Service Delivery Management | E67: Workforce | F67: 0.1 | G67: IT Management | H67: 0.1.5 | I67: IT Human Capital Management | J67: 2.1 | K67: Internal Labor | L67: 2.1.1 | M67: Expense | N67: General Management: Workforce and Talent Management
A68: 0.12.02 | B68: HR Support Personnel - Contractor | D68: SL0: Service Delivery Management | E68: Workforce | F68: 0.1 | G68: IT Management | H68: 0.1.5 | I68: IT Human Capital Management | J68: 3.1 | K68: External Labor | L68: 3.1.1 | M68: Expense | N68: General Management: Workforce and Talent Management
A69: 0.12.03 | B69: HR Support Systems License | D69: SL0: Service Delivery Management | E69: Technology | F69: 0.1 | G69: IT Management | H69: 0.1.5 | I69: IT Human Capital Management | J69: 6.1 | K69: Software | L69: 6.1.2 | M69: Licensing | N69: General Management: Workforce and Talent Management
A70: 0.12.04 | B70: HR Support Systems Vendor Support | D70: SL0: Service Delivery Management | E70: Technology | F70: 0.1 | G70: IT Management | H70: 0.1.5 | I70: IT Human Capital Management | J70: 6.1 | K70: Software | L70: 6.1.3 | M70: Expense | N70: General Management: Workforce and Talent Management
A71: 0.13.01 | B71: Acquisition Support Personnel - Government | C71: Includes pay and other benefits | D71: SL0: Service Delivery Management | E71: Workforce | F71: 0.1 | G71: IT Management | H71: 0.1.4 | I71: IT Vendor Management | J71: 2.1 | K71: Internal Labor | L71: 2.1.1 | M71: Expense | N71: General Management: Supplier Management
A72: 0.13.02 | B72: Acquisition Support Personnel - Contractor | D72: SL0: Service Delivery Management | E72: Workforce | F72: 0.1 | G72: IT Management | H72: 0.1.4 | I72: IT Vendor Management | J72: 3.1 | K72: External Labor | L72: 3.1.1 | M72: Expense | N72: General Management: Supplier Management
A73: 0.13.03 | B73: Acquisition Support Systems License | D73: SL0: Service Delivery Management | E73: Technology | F73: 0.1 | G73: IT Management | H73: 0.1.4 | I73: IT Vendor Management | J73: 6.1 | K73: Software | L73: 6.1.2 | M73: Licensing | N73: General Management: Supplier Management
A74: 0.13.04 | B74: Acquisition Support Systems Vendor Support | D74: SL0: Service Delivery Management | E74: Technology | F74: 0.1 | G74: IT Management | H74: 0.1.4 | I74: IT Vendor Management | J74: 6.1 | K74: Software | L74: 6.1.3 | M74: Expense | N74: General Management: Supplier Management
A75: 0.14.01.01 | B75: Information System Security Assessment (SA) Personnel - Government | C75: Includes pay and other benefits | D75: SL0: Service Delivery Management | E75: Workforce | F75: 0.3 | G75: Security & Compliance | H75: 0.3.1 | I75: Security | J75: 2.1 | K75: Internal Labor | L75: 2.1.1 | M75: Expense | N75: General Management: Information Security Management
A76: 0.14.01.02 | B76: Information System Security Assessment (SA) Personnel - Contractor | D76: SL0: Service Delivery Management | E76: Workforce | F76: 0.3 | G76: Security & Compliance | H76: 0.3.1 | I76: Security | J76: 3.1 | K76: External Labor | L76: 3.1.1 | M76: Expense | N76: General Management: Information Security Management
A77: 0.14.02.01 | B77: Vulnerability Scanning Personnel - Government | C77: Includes pay and other benefits | D77: SL0: Service Delivery Management | E77: Workforce | F77: 0.3 | G77: Security & Compliance | H77: 0.3.1 | I77: Security | J77: 2.1 | K77: Internal Labor | L77: 2.1.1 | M77: Expense | N77: General Management: Information Security Management
A78: 0.14.02.02 | B78: Vulnerability Scanning Personnel - Contractor | D78: SL0: Service Delivery Management | E78: Workforce | F78: 0.3 | G78: Security & Compliance | H78: 0.3.1 | I78: Security | J78: 3.1 | K78: External Labor | L78: 3.1.1 | M78: Expense | N78: General Management: Information Security Management
A79: 0.14.03.01 | B79: Security Documentation Personnel - Government | C79: Includes pay and other benefits | D79: SL0: Service Delivery Management | E79: Workforce | F79: 0.3 | G79: Security & Compliance | H79: 0.3.1 | I79: Security | J79: 2.1 | K79: Internal Labor | L79: 2.1.1 | M79: Expense | N79: General Management: Information Security Management
A80: 0.14.03.02 | B80: Security Documentation Personnel - Contractor | D80: SL0: Service Delivery Management | E80: Workforce | F80: 0.3 | G80: Security & Compliance | H80: 0.3.1 | I80: Security | J80: 3.1 | K80: External Labor | L80: 3.1.1 | M80: Expense | N80: General Management: Information Security Management
A81: 0.14.04.01 | B81: Independent Certification Assessments Personnel - Government | C81: Includes pay and other benefits | D81: SL0: Service Delivery Management | E81: Advisory | F81: 0.3 | G81: Security & Compliance | H81: 0.3.1 | I81: Security | J81: 2.1 | K81: Internal Labor | L81: 2.1.1 | M81: Expense | N81: General Management: Information Security Management
A82: 0.14.04.02 | B82: Independent Certification Assessments Personnel - Contractor | D82: SL0: Service Delivery Management | E82: Advisory | F82: 0.3 | G82: Security & Compliance | H82: 0.3.1 | I82: Security | J82: 3.1 | K82: External Labor | L82: 3.1.1 | M82: Expense | N82: General Management: Information Security Management
A83: 0.14.05.01 | B83: Information System Security Officer (ISSO) Personnel - Government | C83: Includes all aspects of security and security controls related to hardware (facility, hardware, software and network) and software technology stack Includes pay and other benefits | D83: SL0: Service Delivery Management | E83: Workforce | F83: 0.3 | G83: Security & Compliance | H83: 0.3.1 | I83: Security | J83: 2.1 | K83: Internal Labor | L83: 2.1.1 | M83: Expense | N83: General Management: Information Security Management
A84: 0.14.05.02 | B84: Information System Security Officer (ISSO) Personnel - Contractor | C84: Includes all aspects of security and security controls related to hardware (facility, hardware, software and network) and software technology stack | D84: SL0: Service Delivery Management | E84: Workforce | F84: 0.3 | G84: Security & Compliance | H84: 0.3.1 | I84: Security | J84: 3.1 | K84: External Labor | L84: 3.1.1 | M84: Expense | N84: General Management: Information Security Management
A85: 0.14.06.01 | B85: Information System Security Authentication and Access Management Personnel - Government | C85: Access Management which provides identity and access credentials (logical and physical) and authorization, and associated security features for the protection of federal information and information systems from unauthorized access, use, disclosure, disruptions, modification, or destruction Includes pay and other benefits | D85: SL0: Service Delivery Management | E85: Workforce | F85: 0.3 | G85: Security & Compliance | H85: 0.3.1 | I85: Security | J85: 2.1 | K85: Internal Labor | L85: 2.1.1 | M85: Expense | N85: General Management: Information Security Management
A86: 0.14.06.02 | B86: Information System Security Authentication and Access Management Personnel - Contractor | C86: Access Management which provides identity and access credentials (logical and physical) and authorization, and associated security features for the protection of federal information and information systems from unauthorized access, use, disclosure, disruptions, modification, or destruction | D86: SL0: Service Delivery Management | E86: Workforce | F86: 0.3 | G86: Security & Compliance | H86: 0.3.1 | I86: Security | J86: 3.1 | K86: External Labor | L86: 3.1.1 | M86: Expense | N86: General Management: Information Security Management
A87: 0.14.07.01 | B87: Privacy Assessment Personnel - Government | C87: Includes pay and other benefits | D87: SL0: Service Delivery Management | E87: Workforce | F87: 0.3 | G87: Security & Compliance | H87: 0.3.2 | I87: Compliance | J87: 2.1 | K87: Internal Labor | L87: 2.1.1 | M87: Expense | N87: General Management: Information Security Management
A88: 0.14.07.02 | B88: Privacy Assessment Personnel - Contractor | D88: SL0: Service Delivery Management | E88: Workforce | F88: 0.3 | G88: Security & Compliance | H88: 0.3.2 | I88: Compliance | J88: 3.1 | K88: External Labor | L88: 3.1.1 | M88: Expense | N88: General Management: Information Security Management
A89: 0.14.08.01 | B89: Security Risk and Compliance (R&C) Personnel - Government | C89: Includes pay and other benefits | D89: SL0: Service Delivery Management | E89: Workforce | F89: 0.3 | G89: Security & Compliance | H89: 0.3.2 | I89: Compliance | J89: 2.1 | K89: Internal Labor | L89: 2.1.1 | M89: Expense | N89: General Management: Information Security Management
A90: 0.14.08.02 | B90: Security Risk and Compliance (R&C) Personnel - Contractor | D90: SL0: Service Delivery Management | E90: Workforce | F90: 0.3 | G90: Security & Compliance | H90: 0.3.2 | I90: Compliance | J90: 3.1 | K90: External Labor | L90: 3.1.1 | M90: Expense | N90: General Management: Information Security Management
A91: 0.14.09.01 | B91: Security Continuous Monitoring (SCM) Personnel - Government | C91: Includes pay and other benefits | D91: SL0: Service Delivery Management | E91: Workforce | F91: 0.3 | G91: Security & Compliance | H91: 0.3.1 | I91: Security | J91: 2.1 | K91: Internal Labor | L91: 2.1.1 | M91: Expense | N91: General Management: Information Security Management
A92: 0.14.09.02 | B92: Security Continuous Monitoring (SCM) Personnel - Contractor | D92: SL0: Service Delivery Management | E92: Workforce | F92: 0.3 | G92: Security & Compliance | H92: 0.3.1 | I92: Security | J92: 3.1 | K92: External Labor | L92: 3.1.1 | M92: Expense | N92: General Management: Information Security Management
A93: 0.14.10.01 | B93: Information Privacy Tools Support Personnel - Government | C93: Includes pay and other benefits | D93: SL0: Service Delivery Management | E93: Workforce | F93: 0.3 | G93: Security & Compliance | H93: 0.3.2 | I93: Compliance | J93: 2.1 | K93: Internal Labor | L93: 2.1.1 | M93: Expense | N93: General Management: Information Security Management
A94: 0.14.10.02 | B94: Information Privacy Tools Support Personnel - Contractor | D94: SL0: Service Delivery Management | E94: Workforce | F94: 0.3 | G94: Security & Compliance | H94: 0.3.2 | I94: Compliance | J94: 3.1 | K94: External Labor | L94: 3.1.1 | M94: Expense | N94: General Management: Information Security Management
A95: 0.14.10.03 | B95: Information Privacy Tools License | D95: SL0: Service Delivery Management | E95: Technology | F95: 0.3 | G95: Security & Compliance | H95: 0.3.2 | I95: Compliance | J95: 6.1 | K95: Software | L95: 6.1.2 | M95: Licensing | N95: General Management: Information Security Management
A96: 0.14.10.04 | B96: Information Privacy Tools Vendor Support | D96: SL0: Service Delivery Management | E96: Technology | F96: 0.3 | G96: Security & Compliance | H96: 0.3.2 | I96: Compliance | J96: 6.1 | K96: Software | L96: 6.1.3 | M96: Expense | N96: General Management: Information Security Management
A97: 0.14.11.01 | B97: Security Risk and Compliance (R&C) Tools Support Personnel - Government | C97: Includes pay and other benefits | D97: SL0: Service Delivery Management | E97: Workforce | F97: 0.3 | G97: Security & Compliance | H97: 0.3.2 | I97: Compliance | J97: 2.1 | K97: Internal Labor | L97: 2.1.1 | M97: Expense | N97: General Management: Information Security Management
A98: 0.14.11.02 | B98: Security Risk and Compliance (R&C) Tools Support Personnel - Contractor | D98: SL0: Service Delivery Management | E98: Workforce | F98: 0.3 | G98: Security & Compliance | H98: 0.3.2 | I98: Compliance | J98: 3.1 | K98: External Labor | L98: 3.1.1 | M98: Expense | N98: General Management: Information Security Management
A99: 0.14.12.03 | B99: Security Risk and Compliance (R&C) Tools License | D99: SL0: Service Delivery Management | E99: Technology | F99: 0.3 | G99: Security & Compliance | H99: 0.3.2 | I99: Compliance | J99: 6.1 | K99: Software | L99: 6.1.2 | M99: Licensing | N99: General Management: Information Security Management
A100: 0.14.12.04 | B100: security Risk and Compliance (R&C) Tools Vendor Support | D100: SL0: Service Delivery Management | E100: Technology | F100: 0.3 | G100: Security & Compliance | H100: 0.3.2 | I100: Compliance | J100: 6.1 | K100: Software | L100: 6.1.3 | M100: Expense | N100: General Management: Information Security Management
A101: 0.14.10.01 | B101: Security Continuous Monitoring (SCM) Tools Support Personnel - Government | C101: Includes pay and other benefits | D101: SL0: Service Delivery Management | E101: Workforce | F101: 0.3 | G101: Security & Compliance | H101: 0.3.1 | I101: Security | J101: 2.1 | K101: Internal Labor | L101: 2.1.1 | M101: Expense | N101: General Management: Information Security Management
A102: 0.14.10.02 | B102: Security Continuous Monitoring (SCM) Tools Support Personnel - Contractor | D102: SL0: Service Delivery Management | E102: Workforce | F102: 0.3 | G102: Security & Compliance | H102: 0.3.1 | I102: Security | J102: 3.1 | K102: External Labor | L102: 3.1.1 | M102: Expense | N102: General Management: Information Security Management
A103: 0.14.10.03 | B103: Security Continuous Monitoring (SCM) Tools License | D103: SL0: Service Delivery Management | E103: Technology | F103: 0.3 | G103: Security & Compliance | H103: 0.3.1 | I103: Security | J103: 6.1 | K103: Software | L103: 6.1.2 | M103: Licensing | N103: General Management: Information Security Management
A104: 0.14.10.04 | B104: Security Continuous Monitoring (SCM) Tools Vendor Support | D104: SL0: Service Delivery Management | E104: Technology | F104: 0.3 | G104: Security & Compliance | H104: 0.3.1 | I104: Security | J104: 6.1 | K104: Software | L104: 6.1.3 | M104: Expense | N104: General Management: Information Security Management
A105: 0.15.01.01 | B105: Disaster Recovery (DR) Personnel - Government | C105: Includes pay and other benefits | D105: SL0: Service Delivery Management | E105: Workforce | F105: 0.3 | G105: Security & Compliance | H105: 0.3.3 | I105: Disaster Recovery | J105: 2.1 | K105: Internal Labor | L105: 2.1.1 | M105: Expense | N105: Service Management: Service Continuity Management
A106: 0.15.01.02 | B106: Disaster Recovery (DR) Personnel - Contractor | D106: SL0: Service Delivery Management | E106: Workforce | F106: 0.3 | G106: Security & Compliance | H106: 0.3.3 | I106: Disaster Recovery | J106: 3.1 | K106: External Labor | L106: 3.1.1 | M106: Expense | N106: Service Management: Service Continuity Management
A107: 0.15.02.01 | B107: Continuity of Operations (COOP) Personnel - Government | C107: Includes pay and other benefits | D107: SL0: Service Delivery Management | E107: Workforce | F107: 6.3 | G107: Compliance & Controls | H107: 6.3.3 | I107: Business Continuity of Operations | J107: 2.1 | K107: Internal Labor | L107: 2.1.1 | M107: Expense | N107: Service Management: Service Continuity Management
A108: 0.15.02.02 | B108: Continuity of Operations (COOP) Personnel - Contractor | D108: SL0: Service Delivery Management | E108: Workforce | F108: 6.3 | G108: Compliance & Controls | H108: 6.3.3 | I108: Business Continuity of Operations | J108: 3.1 | K108: External Labor | L108: 3.1.1 | M108: Expense | N108: Service Management: Service Continuity Management
A109: 0.16.01 | B109: Federal Records Management Personnel - Government | C109: Includes pay and other benefits | D109: SL0: Service Delivery Management | E109: Workforce | F109: 0.3 | G109: Security & Compliance | H109: 0.3.6 | I109: Federal Records Mgmt | J109: 2.1 | K109: Internal Labor | L109: 2.1.1 | M109: Expense | N109: General Management: Information Security Management
A110: 0.16.02 | B110: Federal Records Management Personnel - Contractor | D110: SL0: Service Delivery Management | E110: Workforce | F110: 0.3 | G110: Security & Compliance | H110: 0.3.6 | I110: Federal Records Mgmt | J110: 3.1 | K110: External Labor | L110: 3.1.1 | M110: Expense | N110: General Management: Information Security Management
A111: 0.16.03.01 | B111: Federal Records Management Tools Support Personnel - Government | C111: Includes pay and other benefits | D111: SL0: Service Delivery Management | E111: Workforce | F111: 0.3 | G111: Security & Compliance | H111: 0.3.6 | I111: Federal Records Mgmt | J111: 2.1 | K111: Internal Labor | L111: 2.1.1 | M111: Expense | N111: General Management: Information Security Management
A112: 0.16.03.02 | B112: Federal Records Management Tools Support Personnel - Contractor | D112: SL0: Service Delivery Management | E112: Workforce | F112: 0.3 | G112: Security & Compliance | H112: 0.3.6 | I112: Federal Records Mgmt | J112: 3.1 | K112: External Labor | L112: 3.1.1 | M112: Expense | N112: General Management: Information Security Management
A113: 0.16.03.03 | B113: Federal Records Management Tools Software License | D113: SL0: Service Delivery Management | E113: Technology | F113: 0.3 | G113: Security & Compliance | H113: 0.3.6 | I113: Federal Records Mgmt | J113: 6.1 | K113: Software | L113: 6.1.2 | M113: Licensing | N113: General Management: Information Security Management
A114: 0.16.03.04 | B114: Federal Records Management Tools Software Vendor Support | D114: SL0: Service Delivery Management | E114: Technology | F114: 0.3 | G114: Security & Compliance | H114: 0.3.6 | I114: Federal Records Mgmt | J114: 6.1 | K114: Software | L114: 6.1.3 | M114: Expense | N114: General Management: Information Security Management
A115: 0.17.01.01 | B115: Desktop Application Management Personnel - Government | C115: Includes tools and support for desktop applications and productivity tools used by the end-user such as Microsoft Office and collaboration software solutions Includes pay and other benefits | D115: SL0: Service Delivery Management | E115: Workforce | F115: 4.1 | G115: End User | H115: 4.1.3 | I115: End User Software | J115: 2.1 | K115: Internal Labor | L115: 2.1.1 | M115: Expense | N115: Technical Management: Infrastructure and Platform Management
A116: 0.17.01.02 | B116: Desktop Application Management Personnel - Contractor | C116: Includes tools and support for desktop applications and productivity tools used by the end-user such as Microsoft Office and collaboration software solutions | D116: SL0: Service Delivery Management | E116: Workforce | F116: 4.1 | G116: End User | H116: 4.1.3 | I116: End User Software | J116: 3.1 | K116: External Labor | L116: 3.1.1 | M116: Expense | N116: Technical Management: Infrastructure and Platform Management
A117: 0.17.01.03 | B117: Desktop Application Support Personnel - Government | C117: Includes tools and support for desktop applications and productivity tools used by the end-user such as Microsoft Office and collaboration software solutions Includes pay and other benefits | D117: SL0: Service Delivery Management | E117: Workforce | F117: 4.1 | G117: End User | H117: 4.1.3 | I117: End User Software | J117: 2.1 | K117: Internal Labor | L117: 2.1.1 | M117: Expense | N117: Technical Management: Infrastructure and Platform Management
...

Sheet Cost Pools-SubCost Pools
A2: Source: TBM Taxonomy (https://higherlogicdownload.s3.amazonaws.com/TBMCOUNCIL/c15d372f-9951-46c8-9c3f-213c696401b6/UploadedImages/TBM_Taxonomy_V4_0.pdf)
A3: Cost Pool ID | B3: Cost Pool Name | C3: Sub-Cost Pool ID | D3: Sub-Cost Pool Name | E3: Cost Pool / Sub-Cost Pool Description
A4: 2.1 | B4: Internal Labor | E4: Internal Labor includes the full range of personnel costs and activities required for delivering or supporting the IT services – including direct operational activities, support and management and administration activities.
A5: 2.1 | B5: Internal Labor | C5: 2.1.1 | D5: Expense | E5: Employee wages, benefits, expenses & occupancy.
A6: 2.1 | B6: Internal Labor | C6: 2.1.2 | D6: Capital | E6: Capitalized labor (internal employees)
A7: 3.1 | B7: External Labor | E7: External Labor includes the costs of external personnel required for delivering or supporting the IT services – including direct operational activities, support, management and administration activities.
A8: 3.1 | B8: External Labor | C8: 3.1.1 | D8: Expense | E8: External contractor fees, travel, and expenses.
A9: 3.1 | B9: External Labor | C9: 3.1.2 | D9: Capital | E9: Capitalized labor (external contractors)
A10: 4.1 | B10: Facilities and Power | E10: Facilities & Power costs include the floor space as well as the power, cooling, and other utilities costs, environmental control (fire suppression), power distribution, rack infrastructure, outside services and personnel costs related to managing the data center environment.
A11: 4.1 | B11: Facilities and Power | C11: 4.1.1 | D11: Expense | E11: Data center space, power, security and other operating expenses (e.g., co-location facility services, electricity, water, etc.).
A12: 4.1 | B12: Facilities and Power | C12: 4.1.2 | D12: Lease | E12: Data center lease expenditures.
A13: 4.1 | B13: Facilities and Power | C13: 4.1.3 | D13: Maintenance and Support | E13: Data center maintenance & support expenditures.
A14: 4.1 | B14: Facilities and Power | C14: 4.1.4 | D14: Depreciation and Amortization | E14: Data center depreciation of facility build and leasehold improvements (e.g., raised floor investments, power/PDU infrastructure, and rack build-out).
A15: 4.1 | B15: Facilities and Power | C15: 4.1.5 | D15: Capital | E15: Capitalized leasehold improvements
A16: 5.1 | B16: Hardware | E16: Hardware includes all physical technology assets excluding property, office space or raised floor facilities. The range of assets varies by IT Resource Tower; examples include servers, PCs, storage arrays, network appliances, printers and so on. Where a device contains embedded software (firmware), for example in a network firewall, the cost should be reported as hardware even if the software can be upgraded for a separate fee.
A17: 5.1 | B17: Hardware | C17: 5.1.1 | D17: Expense | E17: Hardware expense of non-capitalized purchases (e.g., spare parts, consumables or equipment below capitalization threshold).
A18: 5.1 | B18: Hardware | C18: 5.1.2 | D18: Lease | E18: Hardware lease expenditures (e.g., hardware purchased through a supplier or financial services leasing arrangement).
A19: 5.1 | B19: Hardware | C19: 5.1.3 | D19: Maintenance and Support | E19: Hardware maintenance and support expenditures.
A20: 5.1 | B20: Hardware | C20: 5.1.4 | D20: Depreciation and Amortization | E20: Hardware depreciation of capitalized purchases.
A21: 5.1 | B21: Hardware | C21: 5.1.5 | D21: Capital | E21: Capitalized hardware expenditures
A22: 6.1 | B22: Software | E22: Software includes the licensing, maintenance and support costs for all software including operating system, middleware, databases, system management and administration tools, desktop applications and utilities and business applications. Software costs include enterprise or per instance licenses, client-access licenses, maintenance/update costs, customization fees.
A23: 6.1 | B23: Software | C23: 6.1.1 | D23: Expense | E23: Software expense of non-capitalized software purchases.
A24: 6.1 | B24: Software | C24: 6.1.2 | D24: Licensing | E24: Software license expenditures for the use of non-SaaS provided software. SaaS subscriptions belong under Outside Services > Cloud Service Providers.
A25: 6.1 | B25: Software | C25: 6.1.3 | D25: Maintenance and Support | E25: Software maintenance and support expenditures.
A26: 6.1 | B26: Software | C26: 6.1.4 | D26: Depreciation and Amortization | E26: Software depreciation of capitalized software license purchases & software development efforts.
A27: 6.1 | B27: Software | C27: 6.1.5 | D27: Capital | E27: Capitalized software expenditures
A28: 7.1 | B28: Telecom | E28: Includes all telecommunications charges, including leased line, domestic and international voice (including mobile), MPLS, ISP and other charges. Telecom costs include the circuits and any associated usage fees for providing voice and/or data telecommunication services between data centers, office locations, the internet and any customer, supplier, or partner. This is typically transmission across the wide area network (WAN).
A29: 7.1 | B29: Telecom | C29: 7.1.1 | D29: Expense | E29: Voice and data network connectivity expenses including circuit and usage expenditures.
A30: 7.1 | B30: Telecom | C30: 7.1.2 | D30: Lease | E30: Telecom lease expenditures.
A31: 7.1 | B31: Telecom | C31: 7.1.3 | D31: Maintenance and Support | E31: Telecom maintenance & support expenditures.
A32: 7.1 | B32: Telecom | C32: 7.1.4 | D32: Depreciation and Amortization | E32: Depreciation/amortization of any capitalized telecom expenditures; typically, this will show up under Hardware or Facilities depreciation/amortization.
A33: 7.1 | B33: Telecom | C33: 7.1.5 | D33: Capital | E33: Capitalized telecom expenditures
A34: 8.1 | B34: Other
A35: 8.1 | B35: Other | C35: 8.1.1 | D35: Other | E35: Miscellaneous or non-standard expenses.
A36: 9.1 | B36: Outside Services | E36: Outside Services include IT services purchased from external service providers including consulting services, managed services and public cloud services. Specific examples of outside services include managed network services, cloud storage for end user backup, and externally provided email services.
A37: 9.1 | B37: Outside Services | C37: 9.1.1 | D37: Consulting | E37: External consulting project-based services.
A38: 9.1 | B38: Outside Services | C38: 9.1.2 | D38: Managed Service Providers | E38: External managed service providers.
A39: 9.1 | B39: Outside Services | C39: 9.1.3 | D39: Cloud Service Providers | E39: External public cloud service providers including IaaS, PaaS, and SaaS.
A40: 9.1 | B40: Outside Services | C40: 9.1.4 | D40: Capital | E40: Capitalized services
A41: 10.1 | B41: Internal Services
A42: 10.1 | B42: Internal Services | C42: 10.1.1 | D42: Shared Service | E42: Miscellaneous charges received from other internal shared services groups (e.g., HR service fees from the HR department). Real estate management fees for space and power should be included in the Facilities and Power cost pool.

Sheet ITIL
A2: Source: Information Technology Infrastructure Library (ITIL) - IT Service Management (ITSM) (https://www.axelos.com/best-practice-solutions/itil). ITIL is a registered trademark of AXELOS Limited.
B4: ITIL®4 Management Practices [Top 34 Practices to Follow] (knowledgehut.com)
B5: Practice Area/Practice | C5: Purpose/Description
B6: General Management Practice Area (14) | C6: The 14 General Management Practices are considered commonly across all services and are applicable for the organization as a whole. These provide the views which are to be practiced throughout, irrespective of the type of services or products the organization provides.
B7: Architecture Management | C7: To provide an understanding and view of all the different elements of an organization as a whole and how each of those elements interfaces or interrelate, to enable the organization to achieve its objectives, continuously. It refers to the applicable principles, tools, standards which enable an organization to be managed in a structured way and also enable agility. While we mention architecture management, it refers to all the domains. That is business architecture, service architecture, information architecture, technology architecture, and environment architecture. These can be defined as an integrated architecture in less complex environment of an organization. The business architecture is defined for creating value to an organization and its customers, aligning to strategy of an organization. The service architecture is defined for each service provided by an organization and it has to be fit in and align to the business architecture. It defines service models, structure, activities, flow of resources, their interactions, templates required etc. The information architecture considers the logical & physical data assets of an organization and depicts how the information; which is a valuable asset of an organization; is managed and measured to create value. It is also important to consider the importance of accuracy, completeness, and accessibility of information while defining the Information architecture. Environmental architecture considers the external factors that impact the organization which includes organizational, political, legal, regulatory, ecological, social, technological etc., These cannot be defined, but have to be considered, while defining, developing and managing the organization, services, products etc.
B8: Continual Improvement | C8: To ensure continuous alignment of service and practice of an organization, by identifying and improving them on a continual basis. This requires Purpose consideration of changing business needs, consumer behavior, changing market scenarios etc. The improvement opportunity has to be looked at by considering all the components of services, products, processes and service as a whole. The improvement of services is a continual affair, this cannot be ignored. It is essential to keep the demand for the services high and there should be an established continual improvement practice across the organization. It should be an induced ability in the organization, so that every service action (activities, processes, products, people) is always subject to improvement. As part of continual improvement practices, an organization should ensure that there is a dedicated effort on continual basis to improve services through continuous measurement. Teams have to dedicate a certain amount of time for focusing on improvements. It is to be understood, “At any given point in time, there are opportunities for improvement” and keep identifying the improvement opportunities. Description:B5 • Continual improvement is not a single team or individual’s job; it should be the way of providing services and responsibility of everyone. • Continual improvement practice shall consider various techniques to identify, assess, analyze, recommend and implement the improvements at various levels. • The techniques like SWOT (analyzing strength, weakness, Opportunities & Threats), proactive problem management, PDCA, Improvement Kata, Lean methods, concepts of DevOps etc. Are the few techniques, which can be used for continual improvement. • If the thought of continual improvement is induced into the staff members of the organization as a whole, by establishing that as the culture, the contribution towards continual improvement and alignment will become the way of doing the services and conducting the business.
B9: Information Security Management | C9: To ensure the protection of the information of an organization throughout the information lifecycle. In a way ensuring the confidentiality, integrity,Purpose and availability of information, so that the organization’s information is safeguarded from unauthorized access and misuse. The information security management has become the de-facto requirement of modern organizations (irrespective of their business), with the advancement of technology & adoption of IT systems more and more. These technology platforms and IT systems are used for processing data & information, in every transaction of the business. Whether it’s a bank, an organization of civil construction business, entertainment houses like movie theatre, television, or a retail store, Irrespective of the type of business the organization is into, the adaption & adoption of technology platforms and IT systems for conducting their business transaction has become common. With this modern outlook, organizations come across new challenges and to protect the interest of the business Information security framework, policies, procedures have been established. These information security management practices consider & maintain the balance between Prevention, Detection and Correction. Information security management practices should consider all the aspects of an organization and its dynamics so that it remains aligned with organization strategy & protects the interest of the organization. These should apply across the organization and should not be just limited to one or few aspects. In order to support information security enablement in the organization, there should be consideration for establishment of information security framework, policies, processes, risk management, identity and access management, event management, structured (controlled) review & reporting.
B10: Knowledge Management | C10: To ensure the maintenance and improvement of information and knowledge effectively and efficiently for the convenient usage of the information and knowledge throughout the organization. Knowledge and information being the most important and valuable assets of an organization, it is very important to identify, capture, process, maintain and improve these aspects. An organization should consider adapting and adopting a structured approach and ensure defining, building, using (& reusing) and sharing. This involves data processed into information, leading to the creation of knowledge. These are required for all the processes, practices, and services of various forms. Further with the advancement of technology & management practices, and organizations embracing more and more solutions that are technology-driven & use complex systems, the knowledge of management practices have become a critical need. It is important to understand that knowledge is not just information. Knowledge is the application of the information in a specific context. This requires the understanding of the scenario of information processing and application of knowledge. For example: For a service desk, a number of incidents logged during the specific period is information (like during the week 1 the number of incidents logged are 100). Using this information, setting the context to reduce the number of incidents and applying the actions for identifying the possibility of reducing the number of incidents and further applying to reduce the incidents is possible only through knowledge. Note: Information provides the message, whereas knowledge is Know-how.
B11: Measurement and Reporting | C11: To measure and report the performance of the business or services, which would help in making decisions and improving the services & business performance. Further, this will also reduce the level of uncertainty. According to Peter Drucker, an American Management consultant, “If you cannot measure it, you cannot improve it”. This saying, emphasizes on the importance of measurement. Measurement is an essential need for all types of organizations irrespective of their size and complexities. The measurement should be represented or conveyed in a specific way which is readable (to make right interpretation) by the intended personnel. The metrics considered to measure differs at various levels. This is because, the context at each level varies and accordingly the metrics has to be considered to make the right representation and interpretation. For example: While measuring a service as a whole, one would look at the availability of the services as one of the metrics. Whereas, a number of incidents occurred, the time taken to resolve & restore the services will become metrics to measure the operational performance. These metrics measured at operational level have to complement the next levels. In the given example, the reduction in the number of incidents or reduction in time to restore services or both should be complemented by improving the availability of the services. Accordingly, the critical success factors and key performance indicator has to be identified and defined at all levels. Each of the metrics defined should have the right description to interpret. If the target metrics for measuring availability is 95%, then its impact on business has to be described, explained and justified. Only then the metrics of 95% makes sense.
B12: Organizational Change Management | C12: To ensure managing the human aspects of an organization while introducing, managing, modifying a service or a product. This needs an effective change management (for required transformation) of organization to achieve the lasting benefits through smooth and successful implementation of changes. While the business environment is subjected to change and evolution, it is very important to understand these dynamics and ensure the organization will also evolve & align with the change. In addition to that, improving the services, service performance, performance of service assets, etc., are also important. This further emphasizes on transforming people in the organization in terms of behavior and culture for success. People are at the core of organizational change management. So, Organizational change management should ensure establishing, clear and relevant objectives, strong and committed leadership, willing and prepared participation and sustained improvement. Moreover, organizational transformation is not an overnight accomplishment, it is a journey. For an effective organizational change management, there are many models that the organization adopts. One such model which is adopted and organizations are successful in accomplishing the intended objective of transforming an organization is 8 steps model of John P Kotter. While initiating the organizational transformation, identification of the audience who are affected by this transformation, the individuals who can become the champions for the successful transformation, creation of vision and communication of the same effectively, creating quick wins and celebrating quick wins, and continuing to produce more wins has to be ensured by an organization.
B13: Portfolio Management | C13: To ensure that the organization has the right mix of programs, projects, products, and services to execute the organization’s strategy within its funding and resource constraints. Portfolio management focuses on defining, analyzing, approving and and services introduced, monitored, managed and retired by an organization. These decisions are taken after, a thorough analysis of services or products, which are being considered for introduction, modification, improvement etc., if they make sense for the organization strategically, in investment perspective and value. Else the service or products will be retired. The portfolio management can be defined as the coordinated collection of strategic decisions that together enable the most effective balance of organizational change and business as usual. Portfolio management achieves this through: • Developing and applying a systematic framework • Clearly defining products and services and linking them to the achievement of agreed outcomes. • Evaluating and prioritizing incoming product, service, or project proposals and other change initiatives. • Implementing a strategic investment appraisal and decision-making process • Analysing and tracking investments based on the value of products,services, programmes, and projects to the organization and its customers. • Monitoring the performance of the overall portfolio and proposing adjustments in response to any changes in organizational priorities. • Reviewing the portfolios in terms of progress, outcomes, costs, risk, benefits, and strategic contribution. The different portfolio involved are producing/service portfolio, project portfolio, and customer portfolio
B14: Project Management | C14: To ensure success of all the projects in the organization through adaption and adoption of formal project management approach and also ensure keeping the motivation of the people high. Projects are formally defined as a temporary organization formed to produce results & accomplish the outcomes which are unique and create value. This requires the involvement of initiating, planning, delegating, executing, monitoring and controlling all the aspects of the project. The success of a project is determined by the accomplishment of the ultimate objective of the project which is defined while triggering the project. Further a project has to ensure; • Maintaining the current operations of the business effectively and efficiently • Transforming/Changing the business operations to ensure sustained growth and ability to compete in the market place • Improving the products and services, continually • Basically, the project approaches are predictive (or waterfall) and adaptive (or agile). The organization can adapt & adopt the specific approach as per the need of the organization or project and its dynamics. What so ever the approach is, it is required to ensure the consideration for project constraints carefully. That is scope, schedule, cost, quality, resources, and risk. Stakeholder engagement and communication also plays a very important role during the project management, this requires continual identification, analyzing and defining the stakeholder engagement strategy and communication management approaches.
B15: Relationship Management | C15: To ensure engaging and establishing the relationship with all the stakeholders at all levels, right from strategic to tactical levels. This includes the customer, supplier, partner, and functions within the organization. A stakeholder is any entity or individual existing internally and externally, who is impacted or impact and influenced or influence at all levels, because of the action organization takes while doing business, services, or projects. The relationship with the stakeholders has to be established & maintained, for successful management. This includes identifying, analyzing, monitoring and improving relationships throughout. Relationship management is required in all types of business organizations, for achieving success. The relationship management practice has to ensure that all the stakeholder needs, drivers & triggers are well understood. The satisfaction Description and involvement of stakeholders are very crucial and there should be a constructive relationship established between them. This should lead to achieving the desired outcomes of the business effectively and efficiently. An organization should always focus on creating high stakeholder value. That is, • by facilitating value creation for service consumers, • prioritizing the products and services as per the needs of the stakeholders, • mediating the conflicting stakeholder requirements, • effective handling of any stakeholder complaints and escalations.
B16: Risk Management | C16: To ensure the efficient and effective handling of risks of an organization throughout the service value chain and the entire lifecycle of the services/products and business. The term, “risk” refers to the uncertainty of outcomes which are both positive and negative. The positive risks are called opportunities and negative risks are called as threats. The interesting part is that generally the negative risks are mostly considered by organizations ignoring the existence of positive risks. Missing or ignoring to consider the positive risks as risks may result in bigger risks as organizations may fail to take advantage of the positive effects of opportunities. The organization should give high importance for managing risks, so that it can ensure the ongoing sustainability and continuously create value to customers. It should be an integral part of every action (or activities) that the organization performs at all levels. Risk is a part of business, it should be consistent across all levels of an organization, and a culture has to be built in an organization supporting risk management. For effective risk management, the organization should adapt and adopt a practice, supporting the achievement of objectives of organization. Risks are to be identified, assessed and treated throughout the service value system. Risk is central to service value system defined in ITIL®4. For every risk identified, there involves a cause that has to be found through risk assessment and appropriate risk action has to be defined. The assignment of risk owner and risk actionee, ensures the demonstration of accountability towards effective risk management.
... B42: Software Development and Management | C42: To ensure meeting stakeholder needs (both internal and external) by providing the required functionalities, which are reliable, maintainable, compliant and auditable. The software deployment and management focus on ensure the software application are fit for purpose and fit for use so that the customer can get the value. This involves the entire lifecycle, right from ideation till retirement as depicted in the picture “The software lifecycle”. The software lifecycle for ITIL4 The software lifecycle includes ideation, design, develop, test, deploy operate and retire, which continually facilitate value creation for services and products delivered to customers. This also involves improvement of the services and service performances continually until it is retired.
